Workbook

Sheet Products
K1: Product titel | O1: Specificaties | S1: Beschrijving (lang) | W1: USP | AA1: Productinformatie (kort) | AE1: Gerelateerde producten | AF1: Foto's FTP | AG1: Productgroepen AG
A2: Artikel | B2: Omschrijving | C2: Sharon.Hoogland | D2: Administratie | E2: Supplier | H2: Verkoopprijs | I2: Hoofdcategorie | J2: Subcategorie | K2: Artikelnaam | L2: TD - Titel DE | M2: TE - Titel Engels | N2: TF - Titel Frans | O2: SN - Specificatie NL | P2: SD - Specificatie DE | Q2: SE - Specificatie EN | R2: SF - Specificatie FR | S2: BN - Beschrijving NL | T2: BD - Beschrijving DE | U2: BE - Beschrijving Engels | V2: BF - Bechrijving Frans | W2: UN - USP NL | X2: UD - USP DE | Y2: UE - USP Engels | Z2: UF - USP FR | AA2: IN - Productinfo NL | AB2: ID - Productinfo DE | AC2: IE - Productinfo EN | AD2: IF - Productinfo FR | AE2: 4x Artikelcode gescheiden door ; | AF2: Aantallen aangeven | AG2: ZG | AH2: WG | AI2: UG
A3: 1213652DE | B3: Hartpapierhülse 1400 x 154 x 125 mm | C3: 0,000 | D3: 37, Tip Top | E3: 12022, REMA TIP TOP AG | F3: Actief | G3: 4,140 | I3: x | J3: x | AG3: 081
A4: 232086-KERNKLOSLL | B4: Kernklos - 250/105-70 | C4: 0,000 | D4: 34, Verbruikte materialen | F4: Actief | G4: 1,950 | I4: x | J4: x | AG4: 083
A5: 5000043PM | B5: REMA TIP TOP Binnenbandpleister 1 35 mm 30 stuks | C5: 0,000 | D5: 37, Tip Top | E5: 17842, Rema Tip Top Nederland B.V. | F5: Actief | G5: 3,260 | I5: x | J5: x | AG5: 083
A6: 5061982DE | B6: T-Rex Hot Vulc+ 0,5 kg | C6: 0,000 | D6: 37, Tip Top | E6: 12022, REMA TIP TOP AG | F6: Actief | G6: 7,800 | H6: 16.5 | I6: 06_Vulcanization Materials | J6: 06-04_T-Rex Glue for Hot Vulcanization | K6: T-REX Hot Vulc+ ; Lijm voor Warmvulkanisatie | L6: T-REX Hot Vulc+ ; Kleber für Heißverbindung | M6: T-REX Hot Vulc+ ; Glue for Hot Vulcanization | N6: T-REX Hot Vulc+ ; Colle pour vulcanisation à chaud | O6: Blik 0,7 Liter / 0,5 Kg | P6: Dose 0,7 Liter / 0,5 Kg | Q6: Can 0,7 Liter / 0,5 Kg | R6: Pot 0,7 Litre / 0,5 Kg | S6: Gemiddeld verbruik per vierkante meter transportband (alleen richtwaarden) ; 1e laag = ca. 300 g/m2 ; 2e laag = ca. 280 g/m2 ; * afhankelijk van het type weefsel ; ; Overeenkomstig de verordening (EG) nr. 1907/2006 (REACH) bevat dit product geen PBT / vPvB-substanties | T6: Durchschnittlicher Verbrauch pro Quadratmeter Förderband (nur Richtwerte) ; 1. Auftrag = ca. 300g/m² ; 2. Auftrag = ca. 280g/m² ; * abhängig von dem Type des Gewebes | U6: Average consumption per square meter of conveyor belt (guideline values only) ; 1st coat = approx. 300 g/m2 ; 2nd coat = approx. 280 g/m2 ; * depending on the type of belt fabric | V6: Consommation moyenne par mètre carré de bande transporteuse (valeurs indicatives uniquement) ; 1ère couche = env. 300 g/m2 ; 2ème couche = env. 280g/m2 ; * selon le type de tissu de la ceinture | W6: CHC-vrij; Gevaarlijke goederen: Ja; Voor Standaard, K en HR kwaliteit dekrubber ; | X6: Ckw-frei ; Gefahrengut: Ja ; Für Gummideckplatten Standard-, K- und HR-Qualität ; | Y6: CHC-Free ; Dangerous goods: Yes ; For Standard, K and HR quality cover rubber ; | Z6: Sans CHC ; Marchandises dangereuses : Oui ; Pour revêtement en caoutchouc de qualité Standard, K et HR ; | AA6: Lijm voor Warmvulkanisatie ; | AB6: Kleber für die Heißvulkanisation ; | AC6: Glue for hot vulcanization ; | AD6: Colle pour vulcanisation à chaud ; | AE6: 5061983DE ; TUSSENRUBBER-0,8SP ; DEKRUBBER-2MMSP ; TOOL003-KWASTTS | AF6: 5061982DE-1 ; 5061982DE-2 | AG6: 081 | AH6: 090 | AI6: 081 | AJ6: WAGU Heizlösung WTHZN
A7: 5061983DE | B7: T-Rex Hot Vulc+ 3,5 kg | C7: 0,000 | D7: 37, Tip Top | E7: 12022, REMA TIP TOP AG | F7: Actief | G7: 45,300 | H7: 85 | I7: 06_Vulcanization Materials | J7: 06-04_T-Rex Glue for Hot Vulcanization | K7: T-REX Hot Vulc+ ; Lijm voor Warmvulkanisatie | L7: T-REX Hot Vulc+ ; Kleber für Heißverbindung | M7: T-REX Hot Vulc+ ; Glue for Hot Vulcanization | N7: T-REX Hot Vulc+ ; Colle pour vulcanisation à chaud | O7: Emmer 5 Liter / 3,5 Kg | P7: Kanne 5 Liter / 3,5 Kg | Q7: Bucket 5 Liter / 3,5 Kg | R7: Seau 5 Litre / 3,5 Kg | S7: Gemiddeld verbruik per vierkante meter transportband (alleen richtwaarden) ; 1e laag = ca. 300 g/m2 ; 2e laag = ca. 280 g/m2 ; * afhankelijk van het type weefsel ; ; Overeenkomstig de verordening (EG) nr. 1907/2006 (REACH) bevat dit product geen PBT / vPvB-substanties | T7: Durchschnittlicher Verbrauch pro Quadratmeter Förderband (nur Richtwerte) ; 1. Anstrich = ca. 300g/m2 ; 2. Anstrich = ca. 280g/m2 ; * abhängig von dem Type des Gewebes | U7: Average consumption per square meter of conveyor belt (guideline values only) ; 1st coat = approx. 300 g/m2 ; 2nd coat = approx. 280 g/m2 ; * depending on the type of belt fabric | V7: Consommation moyenne par mètre carré de bande transporteuse (valeurs indicatives uniquement) ; 1ère couche = env. 300 g/m2 ; 2ème couche = env. 280g/m2 ; * selon le type de tissu de la ceinture | W7: CHC-vrij; Gevaarlijke goederen: Ja; Voor Standaard, K en HR kwaliteit dekrubber ; | X7: Ckw-frei ; Gefahrengut: Ja ; Für Gummideckplatten Standard-, K- und HR-Qualität ; | Y7: CHC-Free ; Dangerous goods: Yes ; For Standard, K and HR quality cover rubber ; | Z7: Sans CHC ; Marchandises dangereuses : Oui ; Pour revêtement en caoutchouc de qualité Standard, K et HR ; | AA7: Lijm voor Warmvulkanisatie ; | AB7: Kleber für die Heißvulkanisation ; | AC7: Glue for hot vulcanization ; | AD7: Colle pour vulcanisation à chaud ; | AE7: 5061982DE ; TUSSENRUBBER-0,8SP ; DEKRUBBER-2MMSP ; TOOL003-KWASTTS | AF7: 5061983DE-1 | AG7: 081 | AH7: 090 | AI7: 081 | AJ7: WAGU Heizlösung WTHZN
A8: 5061984DE | B8: T-Rex Cleaner 5 liter | C8: 0,000 | D8: 37, Tip Top | E8: 12022, REMA TIP TOP AG | F8: Actief | G8: 29,450 | H8: 51.5 | I8: 06_Vulcanization Materials | J8: 06-01_T-Rex Cleaner | K8: T-Rex Cleaner | L8: T-Rex Reinigung | M8: T-Rex Cleaner | N8: T-Rex Nettoyage | O8: Blik 5 liter | P8: Kanne 5 Liter | Q8: Can 5 liter | R8: Pot 5 liter | S8: Reinigingsmiddel om vet en vuil van rubber te verwijderen om een ​​schone omgeving te creëren voor sterke hechting. ; Voor universeel gebruik met CHC-vrije lijmsystemen, primers, vulkaniseer- en verwarmingsoplossingen. ; Kan worden gebruikt als spray voor het nauwkeurig reinigen van kleine oppervlakken. | T8: Reinigungsmittel zum Entfernen von Fett und Schmutz von Gummi, um eine saubere Umgebung für eine starke Haftung zu schaffen. ; Für den universellen Einsatz mit CKW-freien Klebstoffsystemen, Primern, Vulkanisier- und Heizlösungen. ; Kann als Spray zur präzisen Reinigung kleiner Flächen verwendet werden. | U8: Cleaning solvent to remove grease and dirt from rubber to provide a clean environment for strong adhesion ; For universal use with CHC-free adhesive systems, primers, vulcanizing and heating solutions. ; Can be used as spray for precise cleaning of small areas. | V8: Solvant de nettoyage pour éliminer la graisse et la saleté du caoutchouc afin de fournir un environnement propre pour une adhérence solide ; Pour une utilisation universelle avec des systèmes adhésifs sans CHC, des apprêts, des solutions de vulcanisation et de chauffage. ; Peut être utilisé en spray pour un nettoyage précis de petites surfaces. | W8: CHC-vrij; Gevaarlijke goederen: Ja; Uitstekend olie- en vetoplossend vermogen; Toekomstbestendig, REACH-conform; Zuinig in verbruik; T-REX-reinigingsvloeistoffen kunnen universeel worden gebruikt om olie en vet van oppervlakken te verwijderen en gebruikte borstels te reinigen (d.w.z. CHC-vrije lijmsystemen, primers, vulkanisatie- en verwarmingsoplossingen) | X8: CKW-frei ; Gefahrgut: Ja ; Hervorragend öl- und fettlösend ; Zukunftssicher, REACH-Konformität ; Sparsam im Verbrauch; T-REX Reinigungsflüssigkeiten sind universell einsetzbar zur Entfernung von Öl und Fett auf Oberflächen und zur Reinigung gebrauchter Bürsten (z. B. CKW-freie Klebstoffsysteme, Grundierungen, Vulkanisier- und Heizlösungen) | Y8: CHC-free ; Dangerous goods: Yes ; Excellent oil and grease-dissolving ; Future-proof, REACH compliance ; Economic in consumption ; T-REX cleaning fluids can be universally used to remove oil and grease from surfaces and to clean used brushes (i.e. CHC-free adhesive systems, primers, vulcanizing and heating solutions) | Z8: Sans CHC ; Marchandises dangereuses : Oui ; Excellent dissolvant d'huile et de graisse ; À l'épreuve du temps, conformité REACH ; Economique en consommation ; Les liquides de nettoyage T-REX peuvent être utilisés universellement pour éliminer l'huile et la graisse des surfaces et pour nettoyer les pinceaux usagés (c'est-à-dire les systèmes adhésifs sans CHC, les apprêts, les solutions de vulcanisation et de chauffage) | AE8: 5061982DE ; 5148730DE ; 5148760DE ; 5148770DE | AF8: 5061984DE-1 | AG8: 081 | AH8: 089 | AI8: 041 | AJ8: Reinigungsmittel
A9: 5141490DE | B9: T-Rex Vulc B 200 ltr | C9: 1.984,000 | D9: 37, Tip Top | E9: 12022, REMA TIP TOP AG | F9: Actief | G9: 1.667,930 | H9: 2990 | I9: 06_Vulcanization Materials | J9: 06-03_T-Rex Glue for Cold Vulcanization | K9: T-REX Vulc. B Vat | L9: T-REX Vulc. B Fass | M9: T-REX Vulc. B Barrel | N9: T-REX Vulc. B Fut | O9: Vat 190 kg | P9: Fass 190 kg | Q9: Barrel 190 kg | R9: Fut 190 kg | S9: Koud lassen en repareren van transportbanden met weefselversterkingen; Verlijmen van rubberen onderdelen en voeringen; Verlijmen van elastomeerkappen voor aandrijftrommels | T9: Kaltverbindungen und Reparatur von Fördergurten mit Gewebeverstärkungen; Kleben von Gummiteilen und Auskleidungen; Kleben von Elastomer-Leggings für Antriebstrommeln | U9: Cold splicing and repairs of coveyor belts with fabric reinforcements ; Bonding of rubber components and linings ; Bonding of elastomer laggings for drive pulleys | V9: Jonction et réparation à froid de bandes transporteuses avec renforts en tissu ; Collage de composants en caoutchouc et de revêtements ; Collage de jambières élastomères pour poulies motrices | W9: CHC-vrij; Gevaarlijke goederen: Ja; Uitstekende initiële hechtsterkte; Hoge dynamische draagkracht; Banden met hoge weerstand; Universeel inzetbaar op vele materialen; Toekomstbestendig, REACH-conform; Uitstekende hechting; Bewezen productkwaliteit; Eenvoudig aan te brengen; Zuinig in verbruik; Vult T-REX-slijtagebeschermings- en reparatiesystemen aan met CN-bindingslaag | X9: CKW-frei ; Gefahrgut: Ja ; Hervorragende Anfangshaftung; Hohe dynamische Belastbarkeit ; Hochfeste Bindungen ; Universell einsetzbar auf vielen Materialien; Zukunftssicher, REACH-Konformität ; Hervorragende Haftung; Bewährte Produktqualität; Einfach anzuwenden ; Sparsam im Verbrauch; Ergänzt T-REX Verschleißschutz- und Reparatursysteme mit CN-Haftschicht | Y9: CHC-free ; Dangerous goods: Yes ; Outstanding initial bond strength ; High dynamic load rating ; High-strength bonds ; Can be universally used on many materials ; Future-proof, REACH compliance ; Excellent adhesion ; Proven product quality ; Easy to apply ; Economic in consumption ; Complements T-REX wear protection and repair systems with CN bonding layer | Z9: Sans CHC ; Marchandises dangereuses : Oui ; Force de liaison initiale exceptionnelle ; Capacité de charge dynamique élevée ; Liaisons à haute résistance ; Peut être utilisé universellement sur de nombreux matériaux ; À l'épreuve du temps, conformité REACH ; Excellente adhérence ; Qualité de produit éprouvée ; Facile à appliquer ; Economique en consommation ; Complète les systèmes de protection contre l'usure et de réparation T-REX avec une couche de liaison CN | AE9: 5148760DE ; 5148770DE ; 5148730DE ; 5061984DE | AF9: 5141490DE-1 | AG9: 081 | AH9: 089 | AI9: 082 | AJ9: WTS & WTH 2004
A10: 5148730DE | B10: T-Rex Primer A - 750 g | C10: 0,000 | D10: 37, Tip Top | E10: 12022, REMA TIP TOP AG | F10: Actief | G10: 20,810 | H10: 32.5 | I10: 06_Vulcanization Materials | J10: 06-02_T-Rex Primer | K10: T-REX Primer | L10: T-REX Primer / Grundierung | M10: T-REX Primer | N10: T-REX Primer / Apprêt | O10: Blik 0,75 Kg | P10: Kanne 0,75 Kg | Q10: Can 0,75 Kg | R10: Pot 0,75 Kg | W10: CHC-vrij; Gevaarlijke goederen: Ja; Kleur: grijs ; Toekomstbestendig, REACH-conform; Zuinig in verbruik; Uitstekende hechting in combinatie met T-REX Vulc. B ; Korte droogtijd; Extra tijdelijke bescherming tegen atmosferische corrosie (vochtigheid) | X10: CKW-frei ; Gefahrgut: Ja ; Farbe: Grau; Zukunftssicher, REACH-Konformität ; Sparsam im Verbrauch; Hervorragende Haftung in Kombination mit T-REX Vulc. B ; Kurze Trocknungszeit ; Zusätzlicher temporärer Schutz gegen atmosphärische Korrosion (Feuchtigkeit) | Y10: CHC-free ; Dangerous goods: Yes ; Colour: Gray ; Future-proof, REACH compliance ; Economic in consumption ; Excellent adhesion in combination with T-REX Vulc. B ; Short drying time ; Additional temporary protection for atmospheric corrosion (humidity) | Z10: Sans CHC ; Marchandises dangereuses : Oui ; Couleur : Gris ; À l'épreuve du temps, conformité REACH ; Economique en consommation ; Excellente adhérence en combinaison avec T-REX Vulc. B ; Temps de séchage court ; Protection temporaire supplémentaire contre la corrosion atmosphérique (humidité) | AA10: Primer wordt gebruikt voor het voorbehandelen van metalen oppervlakken van elastomeer-metaalverbindingen voorafgaand aan rubber-metaalverbindingen met hoge dynamische en statische belastingen | AB10: Primer dienen zur Vorbehandlung von Metalloberflächen von Elastomer-Metall-Verbindungen vor Gummi-Metall-Verbindungen mit hohen dynamischen und statischen Belastungen | AC10: Primer are used to pretreat metal surfaces of elastomer-metal bonds prior to rubber-metal bonding with high dynamic and static loads | AD10: Les apprêts sont utilisés pour prétraiter les surfaces métalliques des liaisons élastomère-métal avant la liaison caoutchouc-métal avec des charges dynamiques et statiques élevées | AE10: 5148760DE ; 5148770DE- ; 5061984DE | AF10: 5148730DE-1 | AG10: 081 | AH10: 089 | AI10: 051 | AJ10: Primer
A11: 5148760DE | B11: T-Rex Vulc B - 700 g | C11: 0,000 | D11: 37, Tip Top | E11: 12022, REMA TIP TOP AG | F11: Actief | G11: 8,740 | H11: 16.1 | I11: 06_Vulcanization Materials | J11: 06-03_T-Rex Glue for Cold Vulcanization | K11: T-REX Vulc. B | L11: T-REX Vulc. B | M11: T-REX Vulc. B | N11: T-REX Vulc. B | O11: Blik 0,7 Kg | P11: Kanne 0,7 Kg | Q11: Can 0,7 Kg | R11: Pot 0,7 Kg | S11: Koud lassen en repareren van transportbanden met weefselversterkingen; Verlijmen van rubberen onderdelen en voeringen; Verlijmen van elastomeerkappen voor aandrijftrommels | T11: Kaltverbindungen und Reparatur von Fördergurten mit Gewebeverstärkungen; Kleben von Gummiteilen und Auskleidungen; Kleben von Elastomer-Leggings für Antriebstrommeln | U11: Cold splicing and repairs of coveyor belts with fabric reinforcements ; Bonding of rubber components and linings ; Bonding of elastomer laggings for drive pulleys | V11: Jonction et réparation à froid de bandes transporteuses avec renforts en tissu ; Collage de composants en caoutchouc et de revêtements ; Collage de jambières élastomères pour poulies motrices | W11: CHC-vrij; Gevaarlijke goederen: Ja; Uitstekende initiële hechtsterkte; Hoge dynamische draagkracht; Banden met hoge weerstand; Universeel inzetbaar op vele materialen; Toekomstbestendig, REACH-conform; Uitstekende hechting; Bewezen productkwaliteit; Eenvoudig aan te brengen; Zuinig in verbruik; Vult T-REX-slijtagebeschermings- en reparatiesystemen aan met CN-bindingslaag | X11: CKW-frei ; Gefahrgut: Ja ; Hervorragende Anfangshaftung; Hohe dynamische Belastbarkeit ; Hochfeste Bindungen ; Universell einsetzbar auf vielen Materialien; Zukunftssicher, REACH-Konformität ; Hervorragende Haftung; Bewährte Produktqualität; Einfach anzuwenden ; Sparsam im Verbrauch; Ergänzt T-REX Verschleißschutz- und Reparatursysteme mit CN-Haftschicht | Y11: CHC-free ; Dangerous goods: Yes ; Outstanding initial bond strength ; High dynamic load rating ; High-strength bonds ; Can be universally used on many materials ; Future-proof, REACH compliance ; Excellent adhesion ; Proven product quality ; Easy to apply ; Economic in consumption ; Complements T-REX wear protection and repair systems with CN bonding layer | Z11: Sans CHC ; Marchandises dangereuses : Oui ; Force de liaison initiale exceptionnelle ; Capacité de charge dynamique élevée ; Liaisons à haute résistance ; Peut être utilisé universellement sur de nombreux matériaux ; À l'épreuve du temps, conformité REACH ; Excellente adhérence ; Qualité de produit éprouvée ; Facile à appliquer ; Economique en consommation ; Complète les systèmes de protection contre l'usure et de réparation T-REX avec une couche de liaison CN | AE11: 5141490DE ; 5148770DE ; 5148730DE ; 5061984DE | AF11: 5148760DE-1 ; 5148760DE-2 | AG11: 081 | AH11: 089 | AI11: 082 | AJ11: WTS & WTH 2004
A12: 5148770DE | B12: T-Rex Vulc B-H - 30 g | C12: 0,000 | D12: 37, Tip Top | E12: 12022, REMA TIP TOP AG | F12: Actief | G12: 2,180 | H12: 4.2 | I12: 06_Vulcanization Materials | J12: 06-03_T-Rex Glue for Cold Vulcanization | K12: T-REX Vulc . B Verharder | L12: T-REX Vulc. B Härter | M12: T-REX Vulc. B Hardener | N12: T-REX Vulc. B Durcisseur | O12: Flesje 30 Gr | P12: Flasche 30 Gr | Q12: Bottle 30 Gr | R12: Flacons 30 Gr | S12: Koud lassen en repareren van transportbanden met weefselversterkingen; Verlijmen van rubberen onderdelen en voeringen; Verlijmen van elastomeerkappen voor aandrijftrommels | T12: Kaltverbindungen und Reparatur von Fördergurten mit Gewebeverstärkungen; Kleben von Gummiteilen und Auskleidungen; Kleben von Elastomer-Leggings für Antriebstrommeln | U12: Cold splicing and repairs of coveyor belts with fabric reinforcements ; Bonding of rubber components and linings ; Bonding of elastomer laggings for drive pulleys | V12: Jonction et réparation à froid de bandes transporteuses avec renforts en tissu ; Collage de composants en caoutchouc et de revêtements ; Collage de jambières élastomères pour poulies motrices | W12: CHC-vrij; Gevaarlijke goederen: Ja; Uitstekende initiële hechtsterkte; Hoge dynamische draagkracht; Banden met hoge weerstand; Universeel inzetbaar op vele materialen; Toekomstbestendig, REACH-conform; Uitstekende hechting; Bewezen productkwaliteit; Eenvoudig aan te brengen; Zuinig in verbruik; Vult T-REX-slijtagebeschermings- en reparatiesystemen aan met CN-bindingslaag | X12: CKW-frei ; Gefahrgut: Ja ; Hervorragende Anfangshaftung; Hohe dynamische Tragzahl; Hochfeste Bindungen ; Universell einsetzbar auf vielen Materialien; Zukunftssicher, REACH-Konformität ; Hervorragende Haftung; Bewährte Produktqualität; Einfach anzuwenden ; Sparsam im Verbrauch; Ergänzt T-REX Verschleißschutz- und Reparatursysteme mit CN-Haftschicht | Y12: CHC-free ; Dangerous goods: Yes ; Outstanding initial bond strength ; High dynamic load rating ; High-strength bonds ; Can be universally used on many materials ; Future-proof, REACH compliance ; Excellent adhesion ; Proven product quality ; Easy to apply ; Economic in consumption ; Complements T-REX wear protection and repair systems with CN bonding layer | Z12: Sans CHC ; Marchandises dangereuses : Oui ; Force de liaison initiale exceptionnelle ; Capacité de charge dynamique élevée ; Liaisons à haute résistance ; Peut être utilisé universellement sur de nombreux matériaux ; À l'épreuve du temps, conformité REACH ; Excellente adhérence ; Qualité de produit éprouvée ; Facile à appliquer ; Economique en consommation ; Complète les systèmes de protection contre l'usure et de réparation T-REX avec une couche de liaison CN | AA12: Voor lijm T-REX Vulc. B | AB12: Für Kleber T-REX Vulc. B | AC12: For glue T-REX Vulc. B | AD12: Pour colle T-REX Vulc. B | AE12: 5148760DE ; 5141490DE ; 5061984DE ; 5148730DE | AF12: 5148770DE-1 ; 5148770DE-2 | AG12: 081 | AH12: 089 | AI12: 082 | AJ12: WTS & WTH 2004
A13: 5210222DE | B13: REMALINE 70/CN 25X2000 | C13: 0,000 | D13: 37, Tip Top | E13: 12022, REMA TIP TOP AG | F13: Actief | G13: 10,000 | I13: x | J13: x | AG13: 081
A14: 5210407DE | B14: REMA PERFORMANCE GRIP 70/CN (8x6) 10X2000 | C14: 0,000 | D14: 37, Tip Top | E14: 12022, REMA TIP TOP AG | F14: Actief | G14: 10,000 | I14: x | J14: x | AG14: 081
A15: 5210412DE | B15: REMA PERFORMANCE GRIP 70/CN (8x6) 15X2000 | C15: 0,000 | D15: 37, Tip Top | E15: 12022, REMA TIP TOP AG | F15: Actief | G15: 10,000 | I15: x | J15: x | AG15: 081
A16: 5210417DE | B16: REMA PERFORMANCE GRIP 70/CN (10x8) 15X2000 | C16: 0,000 | D16: 37, Tip Top | E16: 12022, REMA TIP TOP AG | F16: Actief | G16: 10,000 | I16: x | J16: x | AG16: 081
A17: 5210422DE | B17: REMA PERFORMANCE GRIP 70/CN (10x8) 15X2000 | C17: 0,000 | D17: 37, Tip Top | E17: 12022, REMA TIP TOP AG | F17: Actief | G17: 10,000 | I17: x | J17: x | AG17: 081
A18: 5243331DE | B18: DX LINE BL STANDARD 60 Shore T | C18: 0,000 | D18: 37, Tip Top | E18: 12022, REMA TIP TOP AG | F18: Actief | G18: 10,000 | I18: x | J18: x | AG18: 081
A19: 5247440DE | B19: DX SKIRT STANDARD 60 Shore T2 | C19: 0,000 | D19: 37, Tip Top | E19: 12022, REMA TIP TOP AG | F19: Actief | G19: 10,000 | I19: x | J19: x | AG19: 081
A20: 5248120CH | B20: T-Rex Repair Strip -10.000x150x3,2 mm | C20: 0,000 | D20: 37, Tip Top | E20: 12021, REMA TIP TOP (Tianjin) Rubber Technology Co., Ltd. | F20: Actief | G20: 10,000 | H20: 96.2 | I20: 07_Repair Material | J20: 07-05_T-Rex Repair Strips | K20: T-REX Reparatie strip 150mm ; Zonder weefselinlage | L20: T-REX Reparaturband 150mm ; Ohne Gewebeeinlage | M20: T-REX Repair strip 150mm ; Without fabric reinforced | N20: T-REX Bande de réparation 150mm ; Sans pli renforcé | O20: Nr. 2 ; Afmeting: 10.000 x 150 mm ; Dikte: 3,2 mm ; Zonder weefselinlage ; Kleur: Zwart | P20: Nr. 2 ; Abmessung: 10.000 x 150 mm ; Starke: 3,2 mm ; Ohne Gewebeeinlage ; Farbe: Schwarz | Q20: Nr. 2 ; Dimensions: 10.000 x 150 mm ; Thickness: 3,2 mm ; Without fabric ; Colour: Black | R20: Nr. 2 ; Dimensions : 10.000 x 150 mm ; Epaisseur : 3,2 mm ; Sans pli ; Couleur : Noir | AA20: Voor het repareren van dekplaatbeschadigingen in de looprichting van de band; | AB20: Für die Reparatur von Deckplattenschäden in Gurtlaufrichtung ; | AC20: For repairing cover plate damage in the direction of travel of the belt; | AD20: Pour réparer les dommages de la plaque de couverture dans le sens de déplacement de la bande ; | AE20: 5317739CH ; 5315748CH ; 5061984DE ; 5148760DE | AG20: 081 | AH20: 088 | AI20: 024 | AJ20: Reparaturband
A21: 5290177DE | B21: ABB-45 8x2000 | C21: 0,000 | D21: 1, Rubber transportbanden | E21: 12028, REMA TIP TOP DBP B.V. | F21: Actief | G21: 10,000 | I21: x | J21: x | AG21: 081
A22: 5290420DE | B22: REMALINE 40B ROOD 6X2000 | C22: 0,000 | D22: 37, Tip Top | E22: 12022, REMA TIP TOP AG | F22: Actief | G22: 10,010 | I22: x | J22: x | AG22: 081
A23: 5290451DE | B23: REMASKIRT 50/65 12X2000 | C23: 0,000 | D23: 37, Tip Top | E23: 12022, REMA TIP TOP AG | F23: Actief | G23: 5,000 | I23: x | J23: x | AG23: 081
A24: 5291474DE | B24: NK-ROT 12 X 2000 | C24: 0,000 | D24: 1, Rubber transportbanden | E24: 12028, REMA TIP TOP DBP B.V. | F24: Actief | G24: 10,000 | I24: x | J24: x | AG24: 081
A25: 5291522 11DE | B25: NK-ROT 6X2000X10000 | C25: 0,000 | D25: 37, Tip Top | E25: 12022, REMA TIP TOP AG | F25: Actief | G25: 10,010 | I25: x | J25: x | AG25: 081
A26: 5305514CH | B26: T-Rex Repair Patch Size 1 with fabric, 160 x 130 x 3,8 mm | C26: 0,000 | D26: 37, Tip Top | E26: 12021, REMA TIP TOP (Tianjin) Rubber Technology Co., Ltd. | F26: Actief | G26: 1,750 | H26: 3 | I26: 07_Repair Material | J26: 07-04_T-Rex Repair Patches | K26: T-REX Reparatie pleister 160 x 130 mm ; Met weefselinlage | L26: T-REX Reparatur Flicken 160 x 130mm ; Mit Gewebeeinlage | M26: T-REX Repair Patch 160 x 130mm ; With fabric reinforced | N26: T-Rex Rustine avec pli numéro 1, 160 x 130mm | O26: Nr. 1 ; Afmeting: 160 x 130 mm ; Dikte: 3,8 mm ; Met weefselinlage EP 160 ; Kleur: Zwart | P26: Nr. 1 ; Abmessung: 160 x 130 mm ; Starke: 3,8 mm ; Mit Gewebeeinlage EP 160 ; Farbe: Schwarz | Q26: Nr. 1 ; Dimensions: 160 x 130 mm ; Thickness: 3,8 mm ; With fabric reinforced EP 160 ; Colour: Black | R26: Nr. 1 ; Dimensions : 160 x 130 mm ; Epaisseur : 3,8 mm ; Avec tissu renforcé EP 160 ; Couleur : Noir | S26: stk. T-Rex Reparatiepleister maat 1 - met weefsel - afmeting 160 x 130 x 3,8 mm (02684482) | AA26: Voor het repareren van banden | AB26: Für die Reparatur von Durchschlägen ; | AC26: For repairing punctures | AD26: Pour réparer les crevaisons | AE26: 5307512CH ; FOURTHANE-RED-00130002FT ; 5061984DE ; 5148760DE | AF26: 5305514CH-1; 5305514CH-2 | AG26: 081 | AH26: 088 | AI26: 021 | AJ26: Reparaturflicken
A27: 5305521CH | B27: T-Rex Repair Patch Size 2 with fabric, 260 x 200 x 3,8 mm | C27: 0,000 | D27: 37, Tip Top | E27: 12021, REMA TIP TOP (Tianjin) Rubber Technology Co., Ltd. | F27: Actief | G27: 2,360 | H27: 4.15 | I27: 07_Repair Material | J27: 07-04_T-Rex Repair Patches | K27: T-REX Reparatie pleister 260 x 200 mm ; Met weefselinlage | L27: T-REX Reparatur Flicken 260 x 200mm ; Mit Gewebeeinlage | M27: T-REX Repair Patch 260 x 200mm ; With fabric reinforced | N27: T-Rex Rustine avec pli numéro 2, 260 x 200mm | O27: Nr. 2 ; Afmeting: 260 x 200 mm ; Dikte: 3,8 mm ; Met weefselinlage EP 160 ; Kleur: Zwart | P27: Nr. 2 ; Abmessung: 260 x 200 mm ; Starke: 3,8 mm ; Mit Gewebeeinlage EP 160 ; Farbe: Schwarz | Q27: Nr. 2 ; Dimensions: 260 x 200 mm ; Thickness: 3,8 mm ; With fabric reinforced EP 160 ; Colour: Black | R27: Nr. 2 ; Dimensions : 260 x 200 mm ; Epaisseur : 3,8 mm ; Avec tissu renforcé EP 160 ; Couleur : Noir | S27: stk. T-Rex Reparatiepleister maat 2 - met weefsel - afmeting 260 x 200 x 3,8 mm (02684482) | AA27: Voor het repareren van banden | AB27: Für die Reparatur von Durchschlägen ; | AC27: For repairing punctures | AD27: Pour réparer les crevaisons | AE27: 5307529CH ; FOURTHANE-RED-00130002FT ; 5061984DE ; 5148760DE | AF27: 5305521CH-1; 5305521CH-2 | AG27: 081 | AH27: 088 | AI27: 021 | AJ27: Reparaturflicken
A28: 5305538CH | B28: T-Rex Repair Patch Size 3 with fabric, 360 x 270 x 3,8 mm | C28: 0,000 | D28: 37, Tip Top | E28: 12021, REMA TIP TOP (Tianjin) Rubber Technology Co., Ltd. | F28: Actief | G28: 4,130 | H28: 7.25 | I28: 07_Repair Material | J28: 07-04_T-Rex Repair Patches | K28: T-REX Reparatie pleister 360 x 270 mm ; Met weefselinlage | L28: T-REX Reparatur Flicken 360 x 270mm ; Mit Gewebeeinlage | M28: T-REX Repair Patch 360 x 270mm ; With fabric reinforced | N28: T-Rex Rustine avec pli numéro 3, 360 x 270mm | O28: Nr. 3 ; Afmeting: 360 x 270 mm ; Dikte: 3,8 mm ; Met weefselinlage EP 160 ; Kleur: Zwart | P28: Nr. 3 ; Abmessung: 360 x 270 mm ; Starke: 3,8 mm ; Mit Gewebeeinlage EP 160 ; Farbe: Schwarz | Q28: Nr. 3 ; Dimensions: 360 x 270 mm ; Thickness: 3,8 mm ; With fabric reinforced EP 160 ; Colour: Black | R28: Nr. 3 ; Dimensions : 360 x 270 mm ; Epaisseur : 3,8 mm ; Avec tissu renforcé EP 160 ; Couleur : Noir | S28: stk. T-Rex Reparatiepleister maat 3 - met weefsel - afmeting 360 x 270 x 3,8 mm (02684482) | AA28: Voor het repareren van banden | AB28: Für die Reparatur von Durchschlägen ; | AC28: For repairing punctures | AD28: Pour réparer les crevaisons | AE28: 5307536CH ; FOURTHANE-RED-00130002FT ; 5061984DE ; 5148760DE | AF28: 5305538CH-1; 5305538CH-2 | AG28: 081 | AH28: 088 | AI28: 021 | AJ28: Reparaturflicken
A29: 5305540CH | B29: T-Rex Repair Patch Size 4 with fabric, 470 x 360 x 4,4 mm | C29: 0,000 | D29: 37, Tip Top | E29: 12021, REMA TIP TOP (Tianjin) Rubber Technology Co., Ltd. | F29: Actief | G29: 6,230 | H29: 10.75 | I29: 07_Repair Material | J29: 07-04_T-Rex Repair Patches | K29: T-REX Reparatie pleister 470 x 360 mm ; Met weefselinlage | L29: T-REX Reparatur Flicken 470 x 360mm ; Mit Gewebeeinlage | M29: T-REX Repair Patch 470 x 360mm ; With fabric reinforced | N29: T-Rex Rustine avec pli numéro 4, 470 x 360mm | O29: Nr. 4 ; Afmeting: 470 x 360 mm ; Dikte: 4,4 mm ; Met weefselinlage EP 160 ; Kleur: Zwart | P29: Nr. 4 ; Abmessung: 470 x 360 mm ; Starke: 4,4 mm ; Mit Gewebeeinlage EP 160 ; Farbe: Schwarz | Q29: Nr. 4 ; Dimensions: 460 x 360 mm ; Thickness: 4,4 mm ; With fabric reinforced EP 160 ; Colour: Black | R29: Nr. 4 ; Dimensions : 460 x 360 mm ; Epaisseur : 4,4 mm ; Avec tissu renforcé EP 160 ; Couleur : Noir | S29: stk. T-Rex Reparatiepleister maat 4 - met weefsel - afmeting 470 x 360 x 4,4 mm (02684482) | AA29: Voor het repareren van banden | AB29: Für die Reparatur von Durchschlägen ; | AC29: For repairing punctures | AD29: Pour réparer les crevaisons | AE29: 5307536CH ; FOURTHANE-RED-00130002FT ; 5061984DE ; 5148760DE | AF29: 5305540CH-1; 5305540CH-2 | AG29: 081 | AH29: 088 | AI29: 021 | AJ29: Reparaturflicken
A30: 5307512CH | B30: T-Rex Repair Patch Size 1, 160 x 130 x 2,4 mm | C30: 1,440 | D30: 37, Tip Top | E30: 12021, REMA TIP TOP (Tianjin) Rubber Technology Co., Ltd. | F30: Actief | G30: 1,280 | H30: 2.4 | I30: 07_Repair Material | J30: 07-04_T-Rex Repair Patches | K30: T-REX Reparatie pleister 160 x 130 mm ; Zonder weefselinlage | L30: T-REX Reparatur Flicken 160 x 130mm ; Ohne Gewebeeinlage | M30: T-REX Repair Patch 160 x 130mm ; Without fabric reinforced | N30: T-Rex Rustine sans pli numéro 1,160 x 130mm | O30: Nr. 1 ; Afmeting: 160 x 130 mm ; Dikte: 2,2 mm ; Zonder weefselinlage ; Kleur: Zwart | P30: Nr. 1 ; Abmessung: 160 x 130 mm ; Starke: 3,8 mm ; Ohne Gewebeeinlage ; Farbe: Schwarz | Q30: Nr. 1 ; Dimensions: 160 x 130 mm ; Thickness: 2,4 mm ; Without fabric ; Colour: Black | R30: Nr. 1 ; Dimensions : 160 x 130 mm ; Epaisseur : 2,4 mm ; Sans tissu ; Couleur : Noir | S30: stk. T-Rex Reparatiepleister maat 1 - zonder weefsel - afmeting 160 x 130 x 2,4 mm (02684482) | AA30: Voor het repareren van dekschade | AB30: Für die Reparatur von Deckplattenschäden ; | AC30: For repairing cover damage | AD30: Pour réparer les dommages au pont | AE30: 5305514CH ; FOURTHANE-RED-00130002FT ; 5061984DE ; 5148760DE | AF30: 5307512CH-2; 5307512CH-3 | AG30: 081 | AH30: 088 | AI30: 021 | AJ30: Reparaturflicken
A31: 5307529CH | B31: T-Rex Repair Patch Size 2, 260 x 200 x 2,4 mm | C31: 2,160 | D31: 37, Tip Top | E31: 12021, REMA TIP TOP (Tianjin) Rubber Technology Co., Ltd. | F31: Actief | G31: 1,800 | H31: 3.1 | I31: 07_Repair Material | J31: 07-04_T-Rex Repair Patches | K31: T-REX Reparatie pleister 260 x 200 mm ; Zonder weefselinlage | L31: T-REX Reparatur Flicken 260 x 2000mm ; Ohne Gewebeeinlage | M31: T-REX Repair Patch 260 x 200mm ; Without fabric reinforced | N31: T-Rex Rustine sans pli numéro 2, 260 x 200mm | O31: Nr. 2; Afmeting: 260 x 200 mm ; Dikte: 2,4 mm ; Zonder weefselinlage ; Kleur: Zwart | P31: Nr. 2 ; Abmessung: 260 x 200 mm ; Starke: 2,4 mm ; Ohne Gewebeeinlage ; Farbe: Schwarz | Q31: Nr. 2 ; Dimensions: 260 x 200 mm ; Thickness: 2,4 mm ; Without fabric ; Colour: Black | R31: Nr. 2 ; Dimensions : 260 x 200 mm ; Epaisseur : 2,4 mm ; Sans tissu ; Couleur : Noir | S31: stk. T-Rex Reparatiepleister maat 2 - zonder weefsel - afmeting 260 x 200 x 2,4 mm (02684482) | AA31: Voor het repareren van dekschade | AB31: Für die Reparatur von Deckplattenschäden ; | AC31: For repairing cover damage | AD31: Pour réparer les dommages au pont | AE31: 5305521CH ; FOURTHANE-RED-00130002FT ; 5061984DE ; 5148760DE | AF31: 5307529CH-2; 5307529CH-3 | AG31: 081 | AH31: 088 | AI31: 021 | AJ31: Reparaturflicken
A32: 5307536CH | B32: T-Rex Repair Patch Size 3, 360 x 270 x 2,4 mm | C32: 0,000 | D32: 37, Tip Top | E32: 12021, REMA TIP TOP (Tianjin) Rubber Technology Co., Ltd. | F32: Actief | G32: 2,720 | H32: 5.15 | I32: 07_Repair Material | J32: 07-04_T-Rex Repair Patches | K32: T-REX Reparatie pleister 360 x 270 mm ; Zonder weefselinlage | L32: T-REX Reparatur Flicken 360 x 270mm ; Ohne Gewebeeinlage | M32: T-REX Repair Patch 360 x 270mm ; Without fabric reinforced | N32: T-Rex Rustine sans pli numéro 3, 360 x 270mm | O32: Nr. 3 ; Afmeting: 360 x 270 mm ; Dikte: 2,4 mm ; Zonder weefselinlage ; Kleur: Zwart | P32: Nr. 3 ; Abmessung: 360 x 270 mm ; Starke: 2,4 mm ; Ohne Gewebeeinlage ; Farbe: Schwarz | Q32: Nr. 3 ; Dimensions: 360 x 270 mm ; Thickness: 2,4 mm ; Without fabric ; Colour: Black | R32: Nr. 3 ; Dimensions : 360 x 270 mm ; Epaisseur : 2,4 mm ; Sans tissu ; Couleur : Noir | S32: stk. T-Rex Reparatiepleister maat 3 - zonder weefsel - afmeting 360 x 270 x 2,4 mm (02684482) | AA32: Voor het repareren van dekschade | AB32: Für die Reparatur von Deckplattenschäden ; | AC32: For repairing cover damage | AD32: Pour réparer les dommages au pont | AE32: 5305538CH ; FOURTHANE-RED-00130002FT ; 5061984DE ; 5148760DE | AF32: 5307536CH-2; 5307536CH-3 | AG32: 081 | AH32: 088 | AI32: 021 | AJ32: Reparaturflicken
A33: 5315731CH | B33: T-Rex Repair Strip with fabric Nr 1 -10.000x100x3,6 mm | C33: 0,000 | D33: 37, Tip Top | E33: 12021, REMA TIP TOP (Tianjin) Rubber Technology Co., Ltd. | F33: Actief | G33: 51,380 | H33: 83.25 | I33: 07_Repair Material | J33: 07-05_T-Rex Repair Strips | K33: T-REX Reparatie strip 100mm ; Met weefselinlage | L33: T-REX Reparaturband 100mm ; Mit Gewebeeinlage | M33: T-REX Repair strip 100mm ; With fabric reinforced | N33: T-REX Bande de réparation 100mm ; Avec pli renforcé | O33: Nr. 1 ; Afmeting: 10.000 x 100 mm ; Dikte: 3,6 mm ; Met weefselinlage EP 160 ; Kleur: Zwart | P33: Nr. 1 ; Abmessung: 10.000 x 100 mm ; Starke: 3,6 mm ; Mit Gewebeeinlage EP 160 ; Farbe: Schwarz | Q33: Nr. 1 ; Dimensions: 10.000 x 100 mm ; Thickness: 3,6 mm ; With fabric EP160 ; Colour: Black | R33: Nr. 1 ; Dimensions : 10.000 x 100 mm ; Epaisseur : 3,6 mm ; Avec pli EP160 ; Couleur : Noir | AA33: Voor het repareren van lengtescheuren in transportbanden van textiel en staalkoord; | AB33: Für die Reparatur von Längsrissen in Gewebe- und Stahlseilfördergurten ; | AC33: For repairing longitudinal tears in fabric and steel cord conveyor belts; | AD33: Pour réparer les déchirures longitudinales des bandes transporteuses en tissu et en câble d'acier | AE33: 5317739CH ; 5315748CH ; 5061984DE ; 5148760DE | AG33: 081 | AH33: 088 | AI33: 024 | AJ33: Reparaturband
A34: 5315748CH | B34: T-Rex Repair Strip with fabric Nr 2 -10.000x150x4,6 mm | C34: 0,000 | D34: 37, Tip Top | E34: 12021, REMA TIP TOP (Tianjin) Rubber Technology Co., Ltd. | F34: Actief | G34: 84,840 | H34: 147.9 | I34: 07_Repair Material | J34: 07-05_T-Rex Repair Strips | K34: T-REX Reparatie strip 150mm ; Met weefselinlage | L34: T-REX Reparaturband 150mm ; Mit Gewebeeinlage | M34: T-REX Repair strip 150mm ; With fabric reinforced | N34: T-REX Bande de réparation 150mm ; Avec pli renforcé | O34: Nr. 2 ; Afmeting: 10.000 x 150 mm ; Dikte: 4,6 mm ; Met weefselinlage EP 160 ; Kleur: Zwart | P34: Nr. 2 ; Abmessung: 10.000 x 150 mm ; Starke: 4,6 mm ; Mit Gewebeeinlage EP 160 ; Farbe: Schwarz | Q34: Nr. 2 ; Dimensions: 10.000 x 150 mm ; Thickness: 4,6 mm ; With fabric EP160 ; Colour: Black | R34: Nr. 2 ; Dimensions : 10.000 x 150 mm ; Epaisseur : 4,6 mm ; Avec pli EP160 ; Couleur : Noir | AA34: Voor het repareren van lengtescheuren in transportbanden van textiel en staalkoord; | AB34: Für die Reparatur von Längsrissen in Gewebe- und Stahlseilfördergurten ; | AC34: For repairing longitudinal tears in fabric and steel cord conveyor belts; | AD34: Pour réparer les déchirures longitudinales des bandes transporteuses en tissu et en câble d'acier | AE34: 5315731CH ; 5315748CH ; 5061984DE ; 5148760DE | AG34: 081 | AH34: 088 | AI34: 024 | AJ34: Reparaturband
A35: 5315755CH | B35: T-Rex Repair Strip with fabric Nr 3 -10.000x220x4,6 mm | C35: 0,000 | D35: 37, Tip Top | E35: 12021, REMA TIP TOP (Tianjin) Rubber Technology Co., Ltd. | F35: Actief | G35: 130,770 | H35: 238 | I35: 07_Repair Material | J35: 07-05_T-Rex Repair Strips | K35: T-REX Reparatie strip 220mm ; Met weefselinlage | L35: T-REX Reparaturband 220mm ; Mit Gewebeeinlage | M35: T-REX Repair strip 220mm ; With fabric reinforced | N35: T-REX Bande de réparation 220mm ; Avec pli renforcé | O35: Nr. 3 ; Afmeting: 10.000 x 220 mm ; Dikte: 4,6 mm ; Met weefselinlage EP 160 ; Kleur: Zwart | P35: Nr. 3 ; Abmessung: 10.000 x 220 mm ; Starke: 4,6 mm ; Mit Gewebeeinlage EP 160 ; Farbe: Schwarz | Q35: Nr. 3 ; Dimensions: 10.000 x 100 mm ; Thickness: 4,6 mm ; With fabric EP160 ; Colour: Black | R35: Nr. 3 ; Dimensions : 10.000 x 100 mm ; Epaisseur : 4,6 mm ; Avec pli EP160 ; Couleur : Noir | AA35: Voor het repareren van lengtescheuren in transportbanden van textiel en staalkoord; | AB35: Für die Reparatur von Längsrissen in Gewebe- und Stahlseilfördergurten ; | AC35: For repairing longitudinal tears in fabric and steel cord conveyor belts; | AD35: Pour réparer les déchirures longitudinales des bandes transporteuses en tissu et en câble d'acier | AE35: 5315748CH ; 5317752CH ; 5061984DE ; 5148760DE | AG35: 081 | AH35: 088 | AI35: 024 | AJ35: Reparaturband
A36: 5315760CH | B36: T-Rex Repair Strip with fabric Nr 4 -10.000x300x4,8 mm | C36: 0,000 | D36: 37, Tip Top | E36: 12021, REMA TIP TOP (Tianjin) Rubber Technology Co., Ltd. | F36: Actief | G36: 164,200 | H36: 271.4 | I36: 07_Repair Material | J36: 07-05_T-Rex Repair Strips | K36: T-REX Reparatie strip 300mm ; Met weefselinlage | L36: T-REX Reparaturband 300mm ; Mit Gewebeeinlage | M36: T-REX Repair strip 300mm ; With fabric reinforced | N36: T-REX Bande de réparation 300mm ; Avec pli renforcé | O36: Nr. 4 ; Afmeting: 10.000 x 300 mm ; Dikte: 4,8 mm ; Met weefselinlage EP 160 ; Kleur: Zwart | P36: Nr. 4 ; Abmessung: 10.000 x 300 mm ; Starke: 4,8 mm ; Mit Gewebeeinlage EP 160 ; Farbe: Schwarz | Q36: Nr. 4 ; Dimensions: 10.000 x 300 mm ; Thickness: 4,8 mm ; With fabric EP160 ; Colour: Black | R36: Nr. 4 ; Dimensions : 10.000 x 300 mm ; Epaisseur : 4,8 mm ; Avec pli EP160 ; Couleur : Noir | AA36: Voor het repareren van lengtescheuren in transportbanden van textiel en staalkoord; | AB36: Für die Reparatur von Längsrissen in Gewebe- und Stahlseilfördergurten ; | AC36: For repairing longitudinal tears in fabric and steel cord conveyor belts; | AD36: Pour réparer les déchirures longitudinales des bandes transporteuses en tissu et en câble d'acier | AE36: 5315755CH ; 5317768CH ; 5061984DE ; 5148760DE | AG36: 081 | AH36: 088 | AI36: 024 | AJ36: Reparaturband
A37: 5315770CH | B37: T-Rex Repair Strip with fabric Nr 5 -10.000x400x4,8 mm | C37: 0,000 | D37: 37, Tip Top | E37: 12021, REMA TIP TOP (Tianjin) Rubber Technology Co., Ltd. | F37: Actief | G37: 214,010 | H37: 372.75 | I37: 07_Repair Material | J37: 07-05_T-Rex Repair Strips | K37: T-REX Reparatie strip 400mm ; Met weefselinlage | L37: T-REX Reparaturband 400mm ; Mit Gewebeeinlage | M37: T-REX Repair strip 400mm ; With fabric reinforced | N37: T-REX Bande de réparation 400mm ; Avec pli renforcé | O37: Nr. 5 ; Afmeting: 10.000 x 400 mm ; Dikte: 4,8 mm ; Met weefselinlage EP 160 ; Kleur: Zwart | P37: Nr. 5 ; Abmessung: 10.000 x 400 mm ; Starke: 4,8mm ; Mit Gewebeeinlage EP 160 ; Farbe: Schwarz | Q37: Nr. 5 ; Dimensions: 10.000 x 400 mm ; Thickness: 4,8 mm ; With fabric EP160 ; Colour: Black | R37: Nr. 5 ; Dimensions : 10.000 x 400 mm ; Epaisseur : 4,8 mm ; Avec pli EP160 ; Couleur : Noir | AA37: Voor het repareren van lengtescheuren in transportbanden van textiel en staalkoord; | AB37: Für die Reparatur von Längsrissen in Gewebe- und Stahlseilfördergurten ; | AC37: For repairing longitudinal tears in fabric and steel cord conveyor belts; | AD37: Pour réparer les déchirures longitudinales des bandes transporteuses en tissu et en câble d'acier | AE37: 5315760CH ; 5317768CH ; 5061984DE ; 5148760DE | AG37: 081 | AH37: 088 | AI37: 024 | AJ37: Reparaturband
A38: 5317720CH | B38: T-Rex Repair Strip Nr 00-20.000x35x1,7 mm | C38: 0,000 | D38: 37, Tip Top | E38: 12021, REMA TIP TOP (Tianjin) Rubber Technology Co., Ltd. | F38: Actief | G38: 25,360 | H38: 42.8 | I38: 07_Repair Material | J38: 07-05_T-Rex Repair Strips | K38: T-REX Reparatie strip 35mm ; Zonder weefselinlage | L38: T-REX Reparaturband 35mm ; Ohne Gewebeeinlage | M38: T-REX Repair strip 35mm ; Without fabric reinforced | N38: T-REX Bande de réparation 35mm ; Sans pli renforcé | O38: Nr. 00 ; Afmeting: 20.000 x 35 mm ; Dikte: 1,7 mm ; Zonder weefselinlage ; Kleur: Zwart | P38: Nr. 00 ; Abmessung: 20.000 x 35 mm ; Starke: 1,7 mm ; Ohne Gewebeeinlage ; Farbe: Schwarz | Q38: Nr. 00 ; Dimensions: 20.000 x 35 mm ; Thickness: 1,7 mm ; Without fabric ; Colour: Black | R38: Nr. 00 ; Dimensions : 20.000 x 35 mm ; Epaisseur : 1,7 mm ; Sans pli ; Couleur : Noir | AA38: Voor het repareren van dekplaatbeschadigingen in de looprichting van de band; | AB38: Für die Reparatur von Deckplattenschäden in Gurtlaufrichtung ; | AC38: For repairing cover plate damage in the direction of travel of the belt; | AD38: Pour réparer les dommages de la plaque de couverture dans le sens de déplacement de la bande ; | AE38: 5315731CH ; 5317722CH ; 5061984DE ; 5148760DE | AG38: 081 | AH38: 088 | AI38: 024 | AJ38: Reparaturband
A39: 5317722CH | B39: T-Rex Repair Strip Nr 0 -10.000x70x2,2 mm | C39: 0,000 | D39: 37, Tip Top | E39: 12021, REMA TIP TOP (Tianjin) Rubber Technology Co., Ltd. | F39: Actief | G39: 27,610 | H39: 43.9 | I39: 07_Repair Material | J39: 07-05_T-Rex Repair Strips | K39: T-REX Reparatie strip 70mm ; Zonder weefselinlage | L39: T-REX Reparaturband 70mm ; Ohne Gewebeeinlage | M39: T-REX Repair strip 70mm ; Without fabric reinforced | N39: T-REX Bande de réparation 70mm ; Sans pli renforcé | O39: Nr. 0 ; Afmeting: 10.000 x 70 mm ; Dikte: 2,2 mm ; Zonder weefselinlage ; Kleur: Zwart | P39: Nr. 0 ; Abmessung: 10.000 x 70 mm ; Starke: 2,2 mm ; Ohne Gewebeeinlage ; Farbe: Schwarz | Q39: Nr. 0 ; Dimensions: 10.000 x 70 mm ; Thickness: 2,2 mm ; Without fabric ; Colour: Black | R39: Nr. 0 ; Dimensions : 10.000 x 70 mm ; Epaisseur : 2,2 mm ; Sans pli ; Couleur : Noir | AA39: Voor het repareren van dekplaatbeschadigingen in de looprichting van de band; | AB39: Für die Reparatur von Deckplattenschäden in Gurtlaufrichtung ; | AC39: For repairing cover plate damage in the direction of travel of the belt; | AD39: Pour réparer les dommages de la plaque de couverture dans le sens de déplacement de la bande ; | AE39: 5317720CH ; 5315731CH ; 5061984DE ; 5148760DE | AG39: 081 | AH39: 088 | AI39: 024 | AJ39: Reparaturband
A40: 5317739CH | B40: T-Rex Repair Strip Nr 1 -10.000x100x2,2 mm | C40: 0,000 | D40: 37, Tip Top | E40: 12021, REMA TIP TOP (Tianjin) Rubber Technology Co., Ltd. | F40: Actief | G40: 33,790 | H40: 54.9 | I40: 07_Repair Material | J40: 07-05_T-Rex Repair Strips | K40: T-REX Reparatie strip 100mm ; Zonder weefselinlage | L40: T-REX Reparaturband 100mm ; Ohne Gewebeeinlage | M40: T-REX Repair strip 100mm ; Without fabric reinforced | N40: T-REX Bande de réparation 100mm ; Sans pli renforcé | O40: Nr. 1 ; Afmeting: 10.000 x 100 mm ; Dikte: 2,2 mm ; Zonder weefselinlage ; Kleur: Zwart | P40: Nr. 1 ; Abmessung: 10.000 x 100 mm ; Starke: 2,2 mm ; Ohne Gewebeeinlage ; Farbe: Schwarz | Q40: Nr. 1 ; Dimensions: 10.000 x 100 mm ; Thickness: 2,2 mm ; Without fabric ; Colour: Black | R40: Nr. 1 ; Dimensions : 10.000 x 100 mm ; Epaisseur : 2,2 mm ; Sans pli ; Couleur : Noir | AA40: Voor het repareren van dekplaatbeschadigingen in de looprichting van de band; | AB40: Für die Reparatur von Deckplattenschäden in Gurtlaufrichtung ; | AC40: For repairing cover plate damage in the direction of travel of the belt; | AD40: Pour réparer les dommages de la plaque de couverture dans le sens de déplacement de la bande ; | AE40: 5317722CH ; 5315731CH ; 5061984DE ; 5148760DE | AG40: 081 | AH40: 088 | AI40: 024 | AJ40: Reparaturband
A41: 5317746CH | B41: T-Rex Repair Strip Nr 2 -10.000x150x3,2 mm | C41: 0,000 | D41: 37, Tip Top | E41: 12021, REMA TIP TOP (Tianjin) Rubber Technology Co., Ltd. | F41: Actief | G41: 49,980 | H41: 96.2 | I41: 07_Repair Material | J41: 07-05_T-Rex Repair Strips | K41: T-REX Reparatie strip 150mm ; Zonder weefselinlage | L41: T-REX Reparaturband 150mm ; Ohne Gewebeeinlage | M41: T-REX Repair strip 150mm ; Without fabric reinforced | N41: T-REX Bande de réparation 150mm ; Sans pli renforcé | O41: Nr. 2 ; Afmeting: 10.000 x 150 mm ; Dikte: 3,2 mm ; Zonder weefselinlage ; Kleur: Zwart | P41: Nr. 2 ; Abmessung: 10.000 x 150 mm ; Starke: 3,2 mm ; Ohne Gewebeeinlage ; Farbe: Schwarz | Q41: Nr. 2 ; Dimensions: 10.000 x 150 mm ; Thickness: 3,2 mm ; Without fabric ; Colour: Black | R41: Nr. 2 ; Dimensions : 10.000 x 150 mm ; Epaisseur : 3,2 mm ; Sans pli ; Couleur : Noir | AA41: Voor het repareren van dekplaatbeschadigingen in de looprichting van de band; | AB41: Für die Reparatur von Deckplattenschäden in Gurtlaufrichtung ; | AC41: For repairing cover plate damage in the direction of travel of the belt; | AD41: Pour réparer les dommages de la plaque de couverture dans le sens de déplacement de la bande ; | AE41: 5317739CH ; 5315748CH ; 5061984DE ; 5148760DE | AG41: 081 | AH41: 088 | AI41: 024 | AJ41: Reparaturband
A42: 5317746-GB | B42: T-Rex Repair Strip-10.000x150x3,2 mm-Germanbelt | C42: 0,000 | D42: 37, Tip Top | E42: 17345, germanBelt Systems GmbH | F42: Actief | G42: 67,966 | I42: x | J42: x | AE42: 5317746CH | AG42: 083
A43: 5317752CH | B43: T-Rex Repair Strip Nr 3 -10.000x220x3,2 mm | C43: 0,000 | D43: 37, Tip Top | E43: 12021, REMA TIP TOP (Tianjin) Rubber Technology Co., Ltd. | F43: Actief | G43: 77,600 | H43: 149 | I43: 07_Repair Material | J43: 07-05_T-Rex Repair Strips | K43: T-REX Reparatie strip 220mm ; Zonder weefselinlage | L43: T-REX Reparaturband 220mm ; Ohne Gewebeeinlage | M43: T-REX Repair strip 200mm ; Without fabric reinforced | N43: T-REX Bande de réparation 200mm ; Sans pli renforcé | O43: Nr. 3 ; Afmeting: 10.000 x 220 mm ; Dikte: 3,2 mm ; Zonder weefselinlage ; Kleur: Zwart | P43: Nr. 3 ; Abmessung: 10.000 x 220 mm ; Starke: 3,2mm ; Ohne Gewebeeinlage ; Farbe: Schwarz | Q43: Nr. 3 ; Dimensions: 10.000 x 220 mm ; Thickness: 3,2 mm ; Without fabric ; Colour: Black | R43: Nr. 3 ; Dimensions : 10.000 x 220 mm ; Epaisseur : 3,2 mm ; Sans pli ; Couleur : Noir | AA43: Voor het repareren van dekplaatbeschadigingen in de looprichting van de band; | AB43: Für die Reparatur von Deckplattenschäden in Gurtlaufrichtung ; | AC43: For repairing cover plate damage in the direction of travel of the belt; | AD43: Pour réparer les dommages de la plaque de couverture dans le sens de déplacement de la bande ; | AE43: 5317746CH ; 5315755CH ; 5061984DE ; 5148760DE | AG43: 081 | AH43: 088 | AI43: 024 | AJ43: Reparaturband
A44: 5317752-GB | B44: T-Rex Repair Strip-10.000x220x3,2 mm-Germanbelt | C44: 0,000 | D44: 37, Tip Top | E44: 17345, germanBelt Systems GmbH | F44: Actief | G44: 90,000 | I44: x | J44: x | AE44: 5317768CH | AG44: 083
A45: 5317768CH | B45: T-Rex Repair Strip Nr 4 -10.000x300x3,4 mm | C45: 0,000 | D45: 37, Tip Top | E45: 12021, REMA TIP TOP (Tianjin) Rubber Technology Co., Ltd. | F45: Actief | G45: 95,480 | H45: 999 | I45: 07_Repair Material | J45: 07-05_T-Rex Repair Strips | K45: T-REX Reparatie strip 300mm ; Zonder weefselinlage | L45: T-REX Reparaturband 300mm ; Ohne Gewebeeinlage | M45: T-REX Repair strip 300mm ; Without fabric reinforced | N45: T-REX Bande de réparation 300mm ; Sans pli renforcé | O45: Nr. 4 ; Afmeting: 10.000 x 300 mm ; Dikte: 3,4 mm ; Zonder weefselinlage ; Kleur: Zwart | P45: Nr. 4 ; Abmessung: 10.000 x 300 mm ; Starke: 3,4 mm ; Ohne Gewebeeinlage ; Farbe: Schwarz | Q45: Nr. 4 ; Dimensions: 10.000 x 300 mm ; Thickness: 3,4 mm ; Without fabric ; Colour: Black | R45: Nr. 4 ; Dimensions : 10.000 x 300 mm ; Epaisseur : 3,4 mm ; Sans pli ; Couleur : Noir | AA45: Voor het repareren van dekplaatbeschadigingen in de looprichting van de band; | AB45: Für die Reparatur von Deckplattenschäden in Gurtlaufrichtung ; | AC45: For repairing cover plate damage in the direction of travel of the belt; | AD45: Pour réparer les dommages de la plaque de couverture dans le sens de déplacement de la bande ; | AE45: 5317752CH ; 5315760CH ; 5061984DE ; 5148760DE | AG45: 081 | AH45: 088 | AI45: 024 | AJ45: Reparaturband
A46: 5317797-GB | B46: T-Rex Repair Strip-10.000x300x3,4 mm-Germanbelt | C46: 0,000 | D46: 37, Tip Top | E46: 17345, germanBelt Systems GmbH | F46: Actief | G46: 125,000 | I46: x | J46: x | AG46: 083
A47: 5317798-GB | B47: T-Rex Repair Strip-10.000x400x3,4 mm-Germanbelt | C47: 0,000 | D47: 37, Tip Top | E47: 17345, germanBelt Systems GmbH | F47: Actief | G47: 160,000 | I47: x | J47: x | AG47: 083
A48: 5380354TS | B48: Reparaturgewebe EP 160, beids. gummiert-10.000x1.000x1,4 mm | C48: 99,500 | D48: 37, Tip Top | E48: 16411, TSN Tip Top B.V. | F48: Actief | G48: 65,780 | I48: x | J48: x | AG48: 083
A49: 5381078TS | B49: Silikonpapier - 500.000 x 1.200 mm | C49: 1,700 | D49: 37, Tip Top | E49: 16411, TSN Tip Top B.V. | F49: Actief | G49: 0,960 | I49: x | J49: x | AG49: 083
A50: 5397090DE | B50: REMAGRIP CP-X 125 | C50: 0,000 | D50: 37, Tip Top | E50: 12022, REMA TIP TOP AG | F50: Actief | G50: 10,000 | I50: x | J50: x | AG50: 081
A51: 5397220DE | B51: REMAGRIP CK-X 90 | C51: 0,000 | D51: 37, Tip Top | E51: 12022, REMA TIP TOP AG | F51: Actief | G51: 10,000 | I51: x | J51: x | AG51: 081
A52: 5397250DE | B52: REMAGRIP CK-X 50 | C52: 0,000 | D52: 37, Tip Top | E52: 12022, REMA TIP TOP AG | F52: Actief | G52: 10,000 | I52: x | J52: x | AG52: 081
A53: 5397260DE | B53: REMAGRIP CK-X 70 | C53: 0,000 | D53: 37, Tip Top | E53: 12022, REMA TIP TOP AG | F53: Actief | G53: 10,000 | I53: x | J53: x | AG53: 081
A54: 5398070DE | B54: REMAGRIP CK-X 40 | C54: 0,000 | D54: 37, Tip Top | E54: 12022, REMA TIP TOP AG | F54: Actief | G54: 10,000 | I54: x | J54: x | AG54: 081
A55: 5398080DE | B55: REMAGRIP CK-X 40 | C55: 0,000 | D55: 37, Tip Top | E55: 12022, REMA TIP TOP AG | F55: Actief | G55: 10,000 | I55: x | J55: x | AG55: 081
A56: 5398110DE | B56: REMAGRIP CK-X 50 | C56: 0,000 | D56: 37, Tip Top | E56: 12022, REMA TIP TOP AG | F56: Actief | G56: 10,000 | I56: x | J56: x | AG56: 081
A57: 5398140DE | B57: REMAGRIP CK-X 75 | C57: 0,000 | D57: 37, Tip Top | E57: 12022, REMA TIP TOP AG | F57: Actief | G57: 10,000 | I57: x | J57: x | AG57: 081
... A296: AUSGLEICHPLATTE 500X3,0DE | B296: Reparaturausgleichplatte - 10.000 x 500 x 3 mm-00800082 | C296: 0,000 | D296: 37, Tip Top | E296: 12022, REMA TIP TOP AG | F296: Actief | G296: 197,900 | I296: x | J296: x | AG296: 081
A297: BANDKRAMMEN-200LE | B297: Bandkrammen Nr. 200 | C297: 0,730 | D297: 34, Verbruikte materialen | E297: 17013, Leijenaar | F297: Actief | G297: 6,060 | H297: 999 | I297: 07_Repair Material | J297: 07-06_Staples for Quick Repair | K297: T-REX Bandkrammen ; Maat 200 | L297: T-REX Sechszack-Klammern ; Maß 200 | M297: T-REX Shark tooth clips ; Size 200 | N297: T-REX Agrafes dentées ; numéro 200 | O297: Banddikte: ≤ 4 mm ; Tanden: 8 mm ; Verpakking: 100 stuks | P297: Gurtstärke: ≤ 4 mm ; Zähne: 8 mm ; Inhalt: 100 Stück | Q297: Belt thickness: ≤ 4 mm ; Teeth: 8 mm ; Content: 100 pieces | R297: Épaisseur de la bande : ≤ 4 mm ; Dents : 8 mm ; Contenu : 100 pièces | AA297: Bandkrammen worden voornamelijk gebruikt voor het snel repareren van kleine scheuren en insnijdingen in transportbanden of als hulpmiddel bij het intrekken of wisselen van banden. | AB297: Sechszack-Klammern werden vor allem für Schnell-Reparaturen von kleinen Rissen und Schnitten in Fördergurten oder als Montagehilfe beim Einziehen/Wechseln von Gurten verwendet. | AC297: Shark tooth clips are primarily used for quick repair of small tears and cuts in conveyor belts or as an aid for retracting or changing belts. | AD297: Les Agrafes dentées de requin sont principalement utilisés pour la réparation rapide de petites déchirures et coupures dans les bandes transporteuses ou comme aide pour rétracter ou changer les bandes. | AE297: BANDKRAMMEN-201PR ; BANDKRAMMEN-202LE ; BANDKRAMMEN-203PR ; BANDKRAMMEN-204PR | AF297: BANDKRAMMEN-200LE-1; BANDKRAMMEN-200LE-2; BANDKRAMMEN-200LE-3; BANDKRAMMEN-200LE-4 | AG297: 083 | AH297: 092 | AI297: 002 | AJ297: mech. Verbinder Bandnadeln
A298: BANDKRAMMEN-200PR | B298: Bandkrammen Nr. 200 | C298: 0,730 | D298: 34, Verbruikte materialen | E298: 12070, Premier Udyog | F298: Actief | G298: 5,700 | H298: 999 | I298: 07_Repair Material | J298: 07-06_Staples for Quick Repair | K298: T-REX Bandkrammen ; Maat 200 | L298: T-REX Sechszack-Klammern ; Maß 200 | M298: T-REX Shark tooth clips ; Size 200 | N298: T-REX Agrafes dentées ; numéro 200 | O298: Banddikte: ≤ 4 mm ; Tanden: 8 mm ; Verpakking: 100 stuks | P298: Gurtstärke: ≤ 4 mm ; Zähne: 8 mm ; Inhalt: 100 Stück | Q298: Belt thickness: ≤ 4 mm ; Teeth: 8 mm ; Content: 100 pieces | R298: Épaisseur de la bande : ≤ 4 mm ; Dents : 8 mm ; Contenu : 100 pièces | AA298: Bandkrammen worden voornamelijk gebruikt voor het snel repareren van kleine scheuren en insnijdingen in transportbanden of als hulpmiddel bij het intrekken of wisselen van banden. | AB298: Sechszack-Klammern werden vor allem für Schnell-Reparaturen von kleinen Rissen und Schnitten in Fördergurten oder als Montagehilfe beim Einziehen/Wechseln von Gurten verwendet. | AC298: Shark tooth clips are primarily used for quick repair of small tears and cuts in conveyor belts or as an aid for retracting or changing belts. | AD298: Les Agrafes dentées de requin sont principalement utilisés pour la réparation rapide de petites déchirures et coupures dans les bandes transporteuses ou comme aide pour rétracter ou changer les bandes. | AE298: BANDKRAMMEN-201PR ; BANDKRAMMEN-202LE ; BANDKRAMMEN-203PR ; BANDKRAMMEN-204PR | AF298: BANDKRAMMEN-200PR-1; BANDKRAMMEN-200PR-2; BANDKRAMMEN-200PR-3; BANDKRAMMEN-200PR-4 | AG298: 083 | AH298: 092 | AI298: 002 | AJ298: mech. Verbinder Bandnadeln
A299: BANDKRAMMEN-201PR | B299: Bandkrammen Nr. 201 | C299: 0,730 | D299: 34, Verbruikte materialen | E299: 12070, Premier Udyog | F299: Actief | G299: 7,860 | H299: 999 | I299: 07_Repair Material | J299: 07-06_Staples for Quick Repair | K299: T-REX Bandkrammen ; Maat 201 | L299: T-REX Sechszack-Klammern ; Maß 201 | M299: T-REX Shark tooth clips ; Size 201 | N299: T-REX Agrafes dentées ; numéro 201 | O299: Banddikte: 4 mm - 6 mm ; Tanden: 10 mm ; Verpakking: 100 stuks | P299: Gurtstärke: 4 mm - 6 mm ; Zähne: 10 mm ; Inhalt: 100 Stück | Q299: Belt thickness: 4 mm - 6 mm ; Teeth: 10 mm ; Content: 100 pieces | R299: Épaisseur de la bande : 4 mm - 6 mm ; Dents : 10 mm ; Contenu : 100 pièces | AA299: Bandkrammen worden voornamelijk gebruikt voor het snel repareren van kleine scheuren en insnijdingen in transportbanden of als hulpmiddel bij het intrekken of wisselen van banden. | AB299: Sechszack-Klammern werden vor allem für Schnell-Reparaturen von kleinen Rissen und Schnitten in Fördergurten oder als Montagehilfe beim Einziehen/Wechseln von Gurten verwendet. | AC299: Shark tooth clips are primarily used for quick repair of small tears and cuts in conveyor belts or as an aid for retracting or changing belts. | AD299: Les Agrafes dentées de requin sont principalement utilisés pour la réparation rapide de petites déchirures et coupures dans les bandes transporteuses ou comme aide pour rétracter ou changer les bandes. | AE299: BANDKRAMMEN-200PR ; BANDKRAMMEN-202LE ; BANDKRAMMEN-203PR ; BANDKRAMMEN-204PR ; | AF299: BANDKRAMMEN-201PR-1; BANDKRAMMEN-201PR-2; BANDKRAMMEN-201PR-3; BANDKRAMMEN-201PR-4 | AG299: 083 | AH299: 092 | AI299: 002 | AJ299: mech. Verbinder Bandnadeln
A300: BANDKRAMMEN-202BA | B300: Bandkrammen Nr. 202 | C300: 0,000 | D300: 34, Verbruikte materialen | E300: 12143, Bauer Metallwaren | F300: Actief | G300: 4,480 | H300: 999 | I300: 07_Repair Material | J300: 07-06_Staples for Quick Repair | K300: T-REX Bandkrammen ; Maat 202 | L300: T-REX Sechszack-Klammern ; Maß 202 | M300: T-REX Shark tooth clips ; Size 202 | N300: T-REX Agrafes dentées ; numéro 202 | O300: Banddikte: 6 mm - 8 mm ; Tanden: 12 mm ; Verpakking: 100 stuks | P300: Gurtstärke: 6 mm - 8 mm ; Zähne: 12 mm ; Inhalt: 100 Stück | Q300: Belt thickness: 6 mm - 8 mm ; Teeth: 12 mm ; Content: 100 pieces | R300: Épaisseur de la bande : 6 mm - 8 mm ; Dents : 12 mm ; Contenu : 100 pièces | AA300: Bandkrammen worden voornamelijk gebruikt voor het snel repareren van kleine scheuren en insnijdingen in transportbanden of als hulpmiddel bij het intrekken of wisselen van banden. | AB300: Sechszack-Klammern werden vor allem für Schnell-Reparaturen von kleinen Rissen und Schnitten in Fördergurten oder als Montagehilfe beim Einziehen/Wechseln von Gurten verwendet. | AC300: Shark tooth clips are primarily used for quick repair of small tears and cuts in conveyor belts or as an aid for retracting or changing belts. | AD300: Les Agrafes dentées de requin sont principalement utilisés pour la réparation rapide de petites déchirures et coupures dans les bandes transporteuses ou comme aide pour rétracter ou changer les bandes. | AE300: BANDKRAMMEN-200PR ; BANDKRAMMEN-201PR ; BANDKRAMMEN-203PR ; BANDKRAMMEN-204PR ; | AF300: BANDKRAMMEN-202BA-1; BANDKRAMMEN-202BA-2; BANDKRAMMEN-202BA-3; BANDKRAMMEN-202BA-4 | AG300: 083 | AH300: 092 | AI300: 002 | AJ300: mech. Verbinder Bandnadeln
A301: BANDKRAMMEN-202LE | B301: Bandkrammen Nr. 202 | C301: 0,000 | D301: 34, Verbruikte materialen | E301: 17013, Leijenaar | F301: Actief | G301: 9,780 | H301: 999 | I301: 07_Repair Material | J301: 07-06_Staples for Quick Repair | K301: T-REX Bandkrammen ; Maat 202 | L301: T-REX Sechszack-Klammern ; Maß 202 | M301: T-REX Shark tooth clips ; Size 202 | N301: T-REX Agrafes dentées ; numéro 203 | O301: Banddikte: 6 mm - 8 mm ; Tanden: 12 mm ; Verpakking: 100 stuks | P301: Gurtstärke: 6 mm - 8 mm ; Zähne: 12 mm ; Inhalt: 100 Stück | Q301: Belt thickness: 6 mm - 8 mm ; Teeth: 12 mm ; Content: 100 pieces | R301: Épaisseur de la bande : 6 mm - 8 mm ; Dents : 12 mm ; Contenu : 100 pièces | AA301: Bandkrammen worden voornamelijk gebruikt voor het snel repareren van kleine scheuren en insnijdingen in transportbanden of als hulpmiddel bij het intrekken of wisselen van banden. | AB301: Sechszack-Klammern werden vor allem für Schnell-Reparaturen von kleinen Rissen und Schnitten in Fördergurten oder als Montagehilfe beim Einziehen/Wechseln von Gurten verwendet. | AC301: Shark tooth clips are primarily used for quick repair of small tears and cuts in conveyor belts or as an aid for retracting or changing belts. | AD301: Les Agrafes dentées de requin sont principalement utilisés pour la réparation rapide de petites déchirures et coupures dans les bandes transporteuses ou comme aide pour rétracter ou changer les bandes. | AE301: BANDKRAMMEN-200PR ; BANDKRAMMEN-201PR ; BANDKRAMMEN-203PR ; BANDKRAMMEN-204PR ; | AF301: BANDKRAMMEN-202LE-1; BANDKRAMMEN-202LE-2; BANDKRAMMEN-202LE-3; BANDKRAMMEN-202LE-4 | AG301: 083 | AH301: 092 | AI301: 002 | AJ301: mech. Verbinder Bandnadeln
A302: BANDKRAMMEN-203BA | B302: Bandkrammen Nr. 203 | C302: 0,000 | D302: 34, Verbruikte materialen | E302: 12143, Bauer Metallwaren | F302: Actief | G302: 6,560 | H302: 999 | I302: 07_Repair Material | J302: 07-06_Staples for Quick Repair | K302: T-REX Bandkrammen ; Maat 203 | L302: T-REX Sechszack-Klammern ; Maß 203 | M302: T-REX Shark tooth clips ; Size 203 | N302: T-REX Agrafes dentées ; numéro 203 | O302: Banddikte: 8 mm - 10 mm ; Tanden: 16 mm ; Verpakking: 100 stuks | P302: Gurtstärke: 8 mm - 10 mm; Zähne: 16 mm ; Inhalt: 100 Stück | Q302: Belt thickness: 8 mm - 10 mm; Teeth: 16 mm ; Content: 100 pieces | R302: Épaisseur de la bande : 8 mm - 10 mm ; Dents : 16 mm ; Contenu : 100 pièces | AA302: Bandkrammen worden voornamelijk gebruikt voor het snel repareren van kleine scheuren en insnijdingen in transportbanden of als hulpmiddel bij het intrekken of wisselen van banden. | AB302: Sechszack-Klammern werden vor allem für Schnell-Reparaturen von kleinen Rissen und Schnitten in Fördergurten oder als Montagehilfe beim Einziehen/Wechseln von Gurten verwendet. | AC302: Shark tooth clips are primarily used for quick repair of small tears and cuts in conveyor belts or as an aid for retracting or changing belts. | AD302: Les Agrafes dentées de requin sont principalement utilisés pour la réparation rapide de petites déchirures et coupures dans les bandes transporteuses ou comme aide pour rétracter ou changer les bandes. | AE302: BANDKRAMMEN-201PR ; BANDKRAMMEN-202LE ; BANDKRAMMEN-204PR ; BANDKRAMMEN-205PR ; | AF302: BANDKRAMMEN-203BA-1; BANDKRAMMEN-203BA-2; BANDKRAMMEN-203BA-3; BANDKRAMMEN-203BA-4 | AG302: 083 | AH302: 092 | AI302: 002 | AJ302: mech. Verbinder Bandnadeln
A303: BANDKRAMMEN-203PR | B303: Bandkrammen Nr. 203 | C303: 0,000 | D303: 34, Verbruikte materialen | E303: 12070, Premier Udyog | F303: Actief | G303: 12,840 | H303: 999 | I303: 07_Repair Material | J303: 07-06_Staples for Quick Repair | K303: T-REX Bandkrammen ; Maat 203 | L303: T-REX Sechszack-Klammern ; Maß 203 | M303: T-REX Shark tooth clips ; Size 203 | N303: T-REX Agrafes dentées ; numéro 203 | O303: Banddikte: 8 mm - 10 mm ; Tanden: 16 mm ; Verpakking: 100 stuks | P303: Gurtstärke: 8 mm - 10 mm; Zähne: 16 mm ; Inhalt: 100 Stück | Q303: Belt thickness: 8 mm - 10 mm; Teeth: 16 mm ; Content: 100 pieces | R303: Épaisseur de la bande : 8 mm - 10 mm ; Dents : 16 mm ; Contenu : 100 pièces | AA303: Bandkrammen worden voornamelijk gebruikt voor het snel repareren van kleine scheuren en insnijdingen in transportbanden of als hulpmiddel bij het intrekken of wisselen van banden. | AB303: Sechszack-Klammern werden vor allem für Schnell-Reparaturen von kleinen Rissen und Schnitten in Fördergurten oder als Montagehilfe beim Einziehen/Wechseln von Gurten verwendet. | AC303: Shark tooth clips are primarily used for quick repair of small tears and cuts in conveyor belts or as an aid for retracting or changing belts. | AD303: Les Agrafes dentées de requin sont principalement utilisés pour la réparation rapide de petites déchirures et coupures dans les bandes transporteuses ou comme aide pour rétracter ou changer les bandes. | AE303: BANDKRAMMEN-201PR ; BANDKRAMMEN-202LE ; BANDKRAMMEN-204PR ; BANDKRAMMEN-205PR ; | AF303: BANDKRAMMEN-203PR-1; BANDKRAMMEN-203PR-2; BANDKRAMMEN-203PR-3; BANDKRAMMEN-203PR-4 | AG303: 083 | AH303: 092 | AI303: 002 | AJ303: mech. Verbinder Bandnadeln
A304: BANDKRAMMEN-204PR | B304: Bandkrammen Nr. 204 | C304: 0,000 | D304: 34, Verbruikte materialen | E304: 12070, Premier Udyog | F304: Actief | G304: 9,370 | H304: 19.4 | I304: 07_Repair Material | J304: 07-06_Staples for Quick Repair | K304: T-REX Bandkrammen ; Maat 204 | L304: T-REX Sechszack-Klammern ; Maß 204 | M304: T-REX Shark tooth clips ; Size 204 | N304: T-REX Agrafes dentées ; numéro 204 | O304: Banddikte: 10 mm - 13 mm ; Tanden: 20 mm ; Verpakking: 100 stuks | P304: Gurtstärke: 10 mm - 13 mm ; Zähne: 20 mm ; Inhalt: 100 Stück | Q304: Belt thickness: 10 mm - 13 mm ; Teeth: 20 mm ; Content: 100 pieces | R304: Épaisseur de la bande : 10 mm - 13 mm ; Dents : 20 mm ; Contenu : 100 pièces | AA304: Bandkrammen worden voornamelijk gebruikt voor het snel repareren van kleine scheuren en insnijdingen in transportbanden of als hulpmiddel bij het intrekken of wisselen van banden. | AB304: Sechszack-Klammern werden vor allem für Schnell-Reparaturen von kleinen Rissen und Schnitten in Fördergurten oder als Montagehilfe beim Einziehen/Wechseln von Gurten verwendet. | AC304: Shark tooth clips are primarily used for quick repair of small tears and cuts in conveyor belts or as an aid for retracting or changing belts. | AD304: Les Agrafes dentées de requin sont principalement utilisés pour la réparation rapide de petites déchirures et coupures dans les bandes transporteuses ou comme aide pour rétracter ou changer les bandes. | AE304: BANDKRAMMEN-202LE ; BANDKRAMMEN-203PR ; BANDKRAMMEN-205PR ; BANDKRAMMEN-206PR ; | AF304: BANDKRAMMEN-204PR-1; BANDKRAMMEN-204PR-2; BANDKRAMMEN-204PR-3; BANDKRAMMEN-204PR-4 | AG304: 083 | AH304: 092 | AI304: 002 | AJ304: mech. Verbinder Bandnadeln
A305: BANDKRAMMEN-205PR | B305: Bandkrammen Nr. 205 | C305: 0,000 | D305: 34, Verbruikte materialen | E305: 12070, Premier Udyog | F305: Actief | G305: 12,780 | H305: 24.3 | I305: 07_Repair Material | J305: 07-06_Staples for Quick Repair | K305: T-REX Bandkrammen ; Maat 205 | L305: T-REX Sechszack-Klammern ; Maß 205 | M305: T-REX Shark tooth clips ; Size 205 | N305: T-REX Agrafes dentées ; numéro 205 | O305: Banddikte: 13 mm - 15 mm ; Tanden: 23 mm ; Verpakking: 100 stuks | P305: Gurtstärke: 13 mm - 15 mm; Zähne: 23 mm ; Inhalt: 100 Stück | Q305: Belt thickness: 13 mm - 15 mm ; Teeth: 23 mm ; Content: 100 pieces | R305: Épaisseur de la bande : 13 mm - 15 mm ; Dents : 23 mm ; Contenu : 100 pièces | AA305: Bandkrammen worden voornamelijk gebruikt voor het snel repareren van kleine scheuren en insnijdingen in transportbanden of als hulpmiddel bij het intrekken of wisselen van banden. | AB305: Sechszack-Klammern werden vor allem für Schnell-Reparaturen von kleinen Rissen und Schnitten in Fördergurten oder als Montagehilfe beim Einziehen/Wechseln von Gurten verwendet. | AC305: Shark tooth clips are primarily used for quick repair of small tears and cuts in conveyor belts or as an aid for retracting or changing belts. | AD305: Les Agrafes dentées de requin sont principalement utilisés pour la réparation rapide de petites déchirures et coupures dans les bandes transporteuses ou comme aide pour rétracter ou changer les bandes. | AE305: BANDKRAMMEN-203PR ; BANDKRAMMEN-204PR ; BANDKRAMMEN-206PR ; BANDKRAMMEN-207PR | AF305: BANDKRAMMEN-205PR-1; BANDKRAMMEN-205PR-2; BANDKRAMMEN-205PR-3; BANDKRAMMEN-205PR-4 | AG305: 083 | AH305: 092 | AI305: 002 | AJ305: mech. Verbinder Bandnadeln
A306: BANDKRAMMEN-206PR | B306: Bandkrammen Nr. 206 | C306: 0,000 | D306: 34, Verbruikte materialen | E306: 12070, Premier Udyog | F306: Actief | G306: 18,030 | H306: 36.4 | I306: 07_Repair Material | J306: 07-06_Staples for Quick Repair | K306: T-REX Bandkrammen ; Maat 206 | L306: T-REX Sechszack-Klammern ; Maß 206 | M306: T-REX Shark tooth clips ; Size 206 | N306: T-REX Agrafes dentées ; numéro 206 | O306: Banddikte: 15 mm - 18 mm ; Tanden: 29 mm ; Verpakking: 100 stuks | P306: Gurtstärke: 15 mm - 18 mm; Zähne: 29 mm ; Inhalt: 100 Stück | Q306: Belt thickness: 15 mm - 18 mm; Teeth: 29 mm ; Content: 100 pieces | R306: Epaisseur de la bande : 15 mm - 18 mm ; Dents : 29 mm ; Contenu : 100 pièces | AA306: Bandkrammen worden voornamelijk gebruikt voor het snel repareren van kleine scheuren en insnijdingen in transportbanden of als hulpmiddel bij het intrekken of wisselen van banden. | AB306: Sechszack-Klammern werden vor allem für Schnell-Reparaturen von kleinen Rissen und Schnitten in Fördergurten oder als Montagehilfe beim Einziehen/Wechseln von Gurten verwendet. | AC306: Shark tooth clips are primarily used for quick repair of small tears and cuts in conveyor belts or as an aid for retracting or changing belts. | AD306: Les Agrafes dentées de requin sont principalement utilisés pour la réparation rapide de petites déchirures et coupures dans les bandes transporteuses ou comme aide pour rétracter ou changer les bandes. | AE306: BANDKRAMMEN-203PR ; BANDKRAMMEN-204PR ; BANDKRAMMEN-205PR ; BANDKRAMMEN-207PR | AF306: BANDKRAMMEN-206PR-1; BANDKRAMMEN-206PR-2; BANDKRAMMEN-206PR-3; BANDKRAMMEN-206PR-4 | AG306: 083 | AH306: 092 | AI306: 002 | AJ306: mech. Verbinder Bandnadeln
A307: BANDKRAMMEN-207PR | B307: Bandkrammen Nr. 207 | C307: 2,200 | D307: 34, Verbruikte materialen | E307: 12070, Premier Udyog | F307: Actief | G307: 18,570 | H307: 42.5 | I307: 07_Repair Material | J307: 07-06_Staples for Quick Repair | K307: T-REX Bandkrammen ; Maat 207 | L307: T-REX Sechszack-Klammern ; Maß 207 | M307: T-REX Shark tooth clips ; Size 207 | N307: T-REX Agrafes dentées ; numéro 207 | O307: Banddikte: 18 mm - 21 mm ; Tanden: 38 mm ; Verpakking: 50 stuks | P307: Gurtstärke: 18 mm - 21 mm; Zähne: 38 mm ; Inhalt: 50 Stück | Q307: Belt thickness: 18 mm - 21 mm ; Teeth: 38 mm ; Content: 50 pieces | R307: Épaisseur de la bande : 18 mm - 21 mm ; Dents : 38 mm ; Contenu : 50 pièces | AA307: Bandkrammen worden voornamelijk gebruikt voor het snel repareren van kleine scheuren en insnijdingen in transportbanden of als hulpmiddel bij het intrekken of wisselen van banden. | AB307: Sechszack-Klammern werden vor allem für Schnell-Reparaturen von kleinen Rissen und Schnitten in Fördergurten oder als Montagehilfe beim Einziehen/Wechseln von Gurten verwendet. | AC307: Shark tooth clips are primarily used for quick repair of small tears and cuts in conveyor belts or as an aid for retracting or changing belts. | AD307: Les Agrafes dentées de requin sont principalement utilisés pour la réparation rapide de petites déchirures et coupures dans les bandes transporteuses ou comme aide pour rétracter ou changer les bandes. | AE307: BANDKRAMMEN-203PR ; BANDKRAMMEN-204PR ; BANDKRAMMEN-205PR ; BANDKRAMMEN-206PR | AF307: BANDKRAMMEN-207PR-1; BANDKRAMMEN-207PR-2; BANDKRAMMEN-207PR-3; BANDKRAMMEN-207PR-4 | AG307: 083 | AH307: 092 | AI307: 002 | AJ307: mech. Verbinder Bandnadeln
A308: BANDKRAMMEN-FASTENERS-1"PR | B308: Bandkrammen-fasteners-1" (50 stuks) | C308: 0,000 | D308: 34, Verbruikte materialen | E308: 12070, Premier Udyog | F308: Actief | G308: 17,890 | H308: =50*0.8 -> 40 | I308: 07_Repair Material | J308: 07-07_Fasteners | K308: T-REX Verbinders ; Type 1″ | L308: T-REX Gurtverbinder ; Typ 1″ | M308: T-REX Fasteners ; Type 1″ | N308: T-REX Agrafes plates avec boulons Type 1″ | O308: Banddikte: 5 mm - 11 mm ; Verpakking: 50 stuks | P308: Gurtstärke: 5 mm - 11 mm ; Inhalt: 50 stück | Q308: Belt thickness: 5 mm - 11 mm ; Content: 50 pieces | R308: Épaisseur de la bande : 5 mm - 11 mm ; Contenu : 50 pièces | AA308: Snel reparatiemateriaal voor transportbanden in installaties zonder schrapers. Kan worden gebruikt als tijdelijke verbinding en voor reparatie. | AB308: Schnelle Repararaturmaterial für Fördergurte in Förderer ohne Abstreifer. Kann als temporärer Verbinder und für Reparaturen eingesetzt werden. | AC308: Quick repair material for conveyor belts in installations without scrapers. Can be used as a temporary splice and for repair. | AD308: Matériel de réparation rapide pour bandes transporteuses dans des installations sans racleurs. Peut être utilisé comme épissure temporaire et pour la réparation. | AE308: TOOL012-BELTPUNCH-08PR ; BANDKRAMMEN-FASTENERS-1½"PR ; BANDKRAMMEN-FASTENERS-2"PR ; BANDKRAMMEN-FASTENERS-3"PR | AG308: 083 | AH308: 092 | AI308: 002 | AJ308: mech. Verbinder Bandnadeln
A309: BANDKRAMMEN-FASTENERS-1½"PR | B309: Bandkrammen-fasteners-1½"(20 stuks) | C309: 0,000 | D309: 34, Verbruikte materialen | E309: 12070, Premier Udyog | F309: Actief | G309: 8,980 | H309: =20*0.9 -> 18 | I309: 07_Repair Material | J309: 07-07_Fasteners | K309: T-REX Verbinders ; Type 1½″ | L309: T-REX Gurtverbinder ; Typ 1½″ | M309: T-REX Fasteners ; Type 1½″ | N309: T-REX Agrafes plates avec boulons Type 1½″ | O309: Banddikte: 11 mm - 17 mm ; Verpakking: 20 stuks | P309: Gurtstärke: 11 mm - 17 mm ; Inhalt: 20 stück | Q309: Belt thickness: 11 mm - 17 mm ; Content: 20 pieces | R309: Épaisseur de la bande : 11 mm - 17 mm ; Contenu : 20 pièces | AA309: Snel reparatiemateriaal voor transportbanden in installaties zonder schrapers. Kan worden gebruikt als tijdelijke verbinding en voor reparatie. | AB309: Schnelle Repararaturmaterial für Fördergurte in Förderer ohne Abstreifer. Kann als temporärer Verbinder und für Reparaturen eingesetzt werden. | AC309: Quick repair material for conveyor belts in installations without scrapers. Can be used as a temporary splice and for repair. | AD309: Matériel de réparation rapide pour bandes transporteuses dans des installations sans racleurs. Peut être utilisé comme épissure temporaire et pour la réparation. | AE309: TOOL011-CLAMPKEYPR ; TOOL013-BELTPUNCH-10PR ; TOOL014-CLAMPKEY-FOR MACHINEPR ; BANDKRAMMEN-FASTENERS-1"PR | AG309: 083 | AH309: 092 | AI309: 002 | AJ309: mech. Verbinder Bandnadeln
A310: BANDKRAMMEN-FASTENERS-2"PR | B310: Bandkrammen-fasteners-2"(20 stuks) | C310: 0,000 | D310: 34, Verbruikte materialen | E310: 12070, Premier Udyog | F310: Actief | G310: 9,850 | H310: =20*0.95 -> 19 | I310: 07_Repair Material | J310: 07-07_Fasteners | K310: T-REX Verbinders ; Type 2″ | L310: T-REX Gurtverbinder ; Typ 2″ | M310: T-REX Fasteners ; Type 2″ | N310: T-REX Agrafes plates avec boulons Type 2″ | O310: Banddikte: 14 mm - 21 mm ; Verpakking: 20 stuks | P310: Gurtstärke: 14 mm - 21 mm ; Inhalt: 20 stück | Q310: Belt thickness: 14 mm - 21 mm ; Content: 20 pieces | R310: Épaisseur de la bande : 14 mm - 21 mm ; Contenu : 20 pièces | AA310: Snel reparatiemateriaal voor transportbanden in installaties zonder schrapers. Kan worden gebruikt als tijdelijke verbinding en voor reparatie. | AB310: Schnelle Repararaturmaterial für Fördergurte in Förderer ohne Abstreifer. Kann als temporärer Verbinder und für Reparaturen eingesetzt werden. | AC310: Quick repair material for conveyor belts in installations without scrapers. Can be used as a temporary splice and for repair. | AD310: Matériel de réparation rapide pour bandes transporteuses dans des installations sans racleurs. Peut être utilisé comme épissure temporaire et pour la réparation. | AE310: TOOL011-CLAMPKEYPR ; TOOL013-BELTPUNCH-10PR ; TOOL014-CLAMPKEY-FOR MACHINEPR ; BANDKRAMMEN-FASTENERS-1"PR | AG310: 083 | AH310: 092 | AI310: 002 | AJ310: mech. Verbinder Bandnadeln
A311: BANDKRAMMEN-FASTENERS-3"PR | B311: Bandkrammen-fasteners-3"(10 stuks) | C311: 0,000 | D311: 34, Verbruikte materialen | E311: 12070, Premier Udyog | F311: Actief | G311: 10,250 | H311: =10*2.05 -> 20.5 | I311: 07_Repair Material | J311: 07-07_Fasteners | K311: T-REX Verbinders ; Type 3″ | L311: T-REX Gurtverbinder ; Typ 3″ | M311: T-REX Fasteners ; Type 3″ | N311: T-REX Agrafes plates avec boulons Type 3″ | O311: Banddikte: > 24 mm ; Verpakking: 10 stuks | P311: Gurtstärke: > 24 mm ; Inhalt: 10 stück | Q311: Belt thickness: > 24 mm ; Content: 10 pieces | R311: Épaisseur de la bande : > 24 mm ; Contenu : 10 pièces | AA311: Snel reparatiemateriaal voor transportbanden in installaties zonder schrapers. Kan worden gebruikt als tijdelijke verbinding en voor reparatie. | AB311: Schnelle Repararaturmaterial für Fördergurte in Förderer ohne Abstreifer. Kann als temporärer Verbinder und für Reparaturen eingesetzt werden. | AC311: Quick repair material for conveyor belts in installations without scrapers. Can be used as a temporary splice and for repair. | AD311: Matériel de réparation rapide pour bandes transporteuses dans des installations sans racleurs. Peut être utilisé comme épissure temporaire et pour la réparation. | AE311: BANDKRAMMEN-FASTENERS-1½"PR ; BANDKRAMMEN-FASTENERS-2"PR ; BANDKRAMMEN-FASTENERS-3"PR | AG311: 083 | AH311: 092 | AI311: 002 | AJ311: mech. Verbinder Bandnadeln
A312: BANDKRAMMEN-FASTENERS-K27LE | B312: Bandkrammen-fasteners-K27(12 stuks) | C312: 0,000 | D312: 34, Verbruikte materialen | E312: 17013, Leijenaar | F312: Actief | G312: 120,890 | I312: x | J312: x | AG312: 083
A313: BANDKRAMMEN-FASTENERS-MS25LE | B313: Bandkrammen-Fasteners-MS25 | C313: 0,730 | D313: 34, Verbruikte materialen | E313: 17013, Leijenaar | F313: Actief | G313: 41,590 | I313: x | J313: x | AG313: 083
A314: BANDKRAMMEN-FASTENERS-MS35LE | B314: Bandkrammen-Fasteners-MS35 | C314: 0,730 | D314: 34, Verbruikte materialen | E314: 17013, Leijenaar | F314: Actief | G314: 52,560 | I314: x | J314: x | AG314: 083
A315: BANDKRAMMEN-FASTENERS-MS45LE | B315: Bandkrammen-Fasteners-MS45 | C315: 0,730 | D315: 34, Verbruikte materialen | E315: 17013, Leijenaar | F315: Actief | G315: 60,830 | I315: x | J315: x | AG315: 083
A316: BANDOVERKAPPING-1-KUNSTSTOFRO | B316: Bandoverkapping Nr.1,BB400, kunststof | C316: 43,800 | D316: 21, Bandoverkappingen | E316: 12034, Renolit Ondex | F316: Actief | G316: 25,360 | H316: 46.2 | I316: 12_Safety Products | J316: 12-03_Conveyor Belt Covers, PVC | K316: Bandoverkapping PVC ; Bandbreedte 400 mm | L316: Abdeckhauben PVC ; Gurtbreite 400 mm | M316: Belt covers PVC ; Beltwidth 400 mm | N316: Capots en PVC ; Largeur 400 mm | AG316: 083 | AH316: 998 | AI316: 998 | AJ316: Industrie sonstiges
A317: BANDOVERKAPPING-2-KUNSTSTOFRO | B317: Bandoverkapping Nr.2,BB500, kunststof | C317: 43,800 | D317: 21, Bandoverkappingen | E317: 12034, Renolit Ondex | F317: Actief | G317: 27,520 | H317: 49.7 | I317: 12_Safety Products | J317: 12-03_Conveyor Belt Covers, PVC | K317: Bandoverkapping PVC ; Bandbreedte 500 mm | L317: Abdeckhauben PVC ; Gurtbreite 500 mm | M317: Belt covers PVC ; Beltwidth 500 mm | N317: Capots en PVC ; Largeur 500 mm | AG317: 083 | AH317: 998 | AI317: 998 | AJ317: Industrie sonstiges
A318: BANDOVERKAPPING-3-KUNSTSTOFRO | B318: Bandoverkapping Nr.3,BB650, kunststof | C318: 0,000 | D318: 21, Bandoverkappingen | E318: 12034, Renolit Ondex | F318: Actief | G318: 30,530 | H318: 54.3 | I318: 12_Safety Products | J318: 12-03_Conveyor Belt Covers, PVC | K318: Bandoverkapping PVC ; Bandbreedte 650 mm | L318: Abdeckhauben PVC ; Gurtbreite 650 mm | M318: Belt covers PVC ; Beltwidth 650 mm | N318: Capots en PVC ; Largeur 650 mm | AG318: 083 | AH318: 998 | AI318: 998 | AJ318: Industrie sonstiges
A319: BANDOVERKAPPING-4-KUNSTSTOFRO | B319: Bandoverkapping Nr.4,BB800, kunststof | C319: 59,200 | D319: 21, Bandoverkappingen | E319: 12034, Renolit Ondex | F319: Actief | G319: 37,210 | H319: 67 | I319: 12_Safety Products | J319: 12-03_Conveyor Belt Covers, PVC | K319: Bandoverkapping PVC ; Bandbreedte 800 mm | L319: Abdeckhauben PVC ; Gurtbreite 800 mm | M319: Belt covers PVC ; Beltwidth 800 mm | N319: Capots en PVC ; Largeur 800 mm | AG319: 083 | AH319: 998 | AI319: 998 | AJ319: Industrie sonstiges
A320: BANDOVERKAPPING-5-KUNSTSTOFRO | B320: Bandoverkapping Nr.5,BB1000, kunststof | C320: 62,950 | D320: 21, Bandoverkappingen | E320: 12034, Renolit Ondex | F320: Actief | G320: 39,590 | H320: 71.6 | I320: 12_Safety Products | J320: 12-03_Conveyor Belt Covers, PVC | K320: Bandoverkapping PVC ; Bandbreedte 1000 mm | L320: Abdeckhauben PVC ; Gurtbreite 1000 mm | M320: Belt covers PVC ; Beltwidth 1000 mm | N320: Capots en PVC ; Largeur 1000 mm | AG320: 083 | AH320: 998 | AI320: 998 | AJ320: Industrie sonstiges
A321: BANDOVERKAPPING-6-KUNSTSTOFRO | B321: Bandoverkapping Nr.6,BB1200, kunststof | C321: 73,650 | D321: 21, Bandoverkappingen | E321: 12034, Renolit Ondex | F321: Actief | G321: 46,280 | H321: 83.75 | I321: 12_Safety Products | J321: 12-03_Conveyor Belt Covers, PVC | K321: Bandoverkapping PVC ; Bandbreedte 1200 mm | L321: Abdeckhauben PVC ; Gurtbreite 1200 mm | M321: Belt covers PVC ; Beltwidth 1200 mm | N321: Capots en PVC ; Largeur 1200 mm | AG321: 083 | AH321: 998 | AI321: 998 | AJ321: Industrie sonstiges
A322: BANDOVERKAPPING-7-KUNSTSTOFRO | B322: Bandoverkapping Nr.7,BB1400, kunststof | C322: 88,150 | D322: 21, Bandoverkappingen | E322: 12034, Renolit Ondex | F322: Actief | G322: 55,400 | H322: 100.5 | I322: 12_Safety Products | J322: 12-03_Conveyor Belt Covers, PVC | K322: Bandoverkapping PVC ; Bandbreedte 1400 mm | L322: Abdeckhauben PVC ; Gurtbreite 1400 mm | M322: Belt covers PVC ; Beltwidth 1400 mm | N322: Capots en PVC ; Largeur 1400 mm | AG322: 083 | AH322: 998 | AI322: 998 | AJ322: Industrie sonstiges
A323: BANDOVERKAPPING-NR1-STAALPX | B323: Bandoverkapping Nr.1,BB400, staal | C323: 37,300 | D323: 21, Bandoverkappingen | E323: 16914, Phenix Industries | F323: Actief | G323: 18,440 | H323: 43 | I323: 12_Safety Products | J323: 12-02_Conveyor Belt Covers, Steel | K323: Bandoverkapping Staal ; Bandbreedte 400 mm | L323: Abdeckhauben Stahl ; Gurtbreite 400 mm | M323: Belt covers Steel ; Beltwidth 400 mm | N323: Capots en acier ; Largeur 400 mm | AG323: 083 | AH323: 998 | AI323: 998 | AJ323: Industrie sonstiges
A324: BANDOVERKAPPING-NR2-STAALPX | B324: Bandoverkapping Nr.2,BB500, staal | C324: 37,300 | D324: 21, Bandoverkappingen | E324: 16914, Phenix Industries | F324: Actief | G324: 18,670 | H324: 47.2 | I324: 12_Safety Products | J324: 12-02_Conveyor Belt Covers, Steel | K324: Bandoverkapping Staal ; Bandbreedte 500 mm | L324: Abdeckhauben Stahl ; Gurtbreite 500 mm | M324: Belt covers Steel ; Beltwidth 500 mm | N324: Capots en acier ; Largeur 500 mm | AG324: 083 | AH324: 998 | AI324: 998 | AJ324: Industrie sonstiges
A325: BANDOVERKAPPING-NR3-STAALPX | B325: Bandoverkapping Nr.3,BB650, staal | C325: 37,300 | D325: 21, Bandoverkappingen | E325: 16914, Phenix Industries | F325: Actief | G325: 24,090 | H325: 53.2 | I325: 12_Safety Products | J325: 12-02_Conveyor Belt Covers, Steel | K325: Bandoverkapping Staal ; Bandbreedte 650 mm | L325: Abdeckhauben Stahl ; Gurtbreite 650 mm | M325: Belt covers Steel ; Beltwidth 650 mm | N325: Capots en acier ; Largeur 650 mm | AG325: 083 | AH325: 998 | AI325: 998 | AJ325: Industrie sonstiges
A326: BANDOVERKAPPING-NR4-STAALPX | B326: Bandoverkapping Nr.4,BB800, staal | C326: 0,000 | D326: 21, Bandoverkappingen | E326: 16914, Phenix Industries | F326: Actief | G326: 27,350 | H326: 61.6 | I326: 12_Safety Products | J326: 12-02_Conveyor Belt Covers, Steel | K326: Bandoverkapping Staal ; Bandbreedte 800 mm | L326: Abdeckhauben Stahl ; Gurtbreite 800 mm | M326: Belt covers Steel ; Beltwidth 800 mm | N326: Capots en acier ; Largeur 800 mm | AG326: 083 | AH326: 998 | AI326: 998 | AJ326: Industrie sonstiges
A327: BANDOVERKAPPING-NR5-STAALPX | B327: Bandoverkapping Nr.5,BB1000, staal | C327: 0,000 | D327: 21, Bandoverkappingen | E327: 16914, Phenix Industries | F327: Actief | G327: 30,350 | H327: 69.8 | I327: 12_Safety Products | J327: 12-02_Conveyor Belt Covers, Steel | K327: Bandoverkapping Staal ; Bandbreedte 1000 mm | L327: Abdeckhauben Stahl ; Gurtbreite 1000 mm | M327: Belt covers Steel ; Beltwidth 1000 mm | N327: Capots en acier ; Largeur 1000 mm | AG327: 083 | AH327: 998 | AI327: 998 | AJ327: Industrie sonstiges
... A329: BANDOVERKAPPING-NR7-STAALPX | B329: Bandoverkapping Nr.7,BB1400, staal | C329: 54,900 | D329: 21, Bandoverkappingen | E329: 16914, Phenix Industries | F329: Actief | G329: 37,720 | H329: 88.5 | I329: 12_Safety Products | J329: 12-02_Conveyor Belt Covers, Steel | K329: Bandoverkapping Staal ; Bandbreedte 1400 mm | L329: Abdeckhauben Stahl ; Gurtbreite 1400 mm | M329: Belt covers Steel ; Beltwidth 1400 mm | N329: Capots en acier ; Largeur 1400 mm | AG329: 083 | AH329: 998 | AI329: 998 | AJ329: Industrie sonstiges
A330: BELT BRUSH CLEANER RBC-A-100HY | B330: secondary cleaner RBC-A-100 with motor/ rubber brush | C330: 0,000 | D330: 29, Ov.slijtmat. buitenland | E330: 12003, Hsin Yung Chien Co. Ltd. | F330: Actief | G330: 2.200,000 | I330: x | J330: x | AG330: 083
A331: BELT LIFTING STATIONKR | B331: Conveyor Belt Lifting Station | C331: 0,000 | D331: 9, Overige transportbanden | E331: 17614, Krozmet s.c. | F331: Actief | G331: 1.750,000 | H331: 2000 | I331: 05_Tools | J331: 05-01_T-Rex Belt Lifting Station | K331: T-REX Banden hefstation | L331: T-REX Fördergurt Hebestation | M331: T-REX Belt Lifting Station | N331: T-REX Station de relèvement | O331: Lengte 1.150 mm ; Breedte 315 mm ; Minimale hefhoogte 170 mm ; Maximale hefhoogte 470 mm ; Gewicht 14,9 kg | P331: Länge 1.150 mm ; Breite 315 mm ; Mindesthubhöhe 170 mm ; Maximale Hubhöhe 470 mm ; Gewicht 14,9 kg | Q331: Length 1.150 mm ; Width 315 mm ; Minimum lifting height 170 mm ; Maximum lifting height 470 mm ; Weight 14,9 kg ; The belt lifting station consists of: ; - Support beam to be mounted on the conveyor frame ; - Lifting arm to adjust height of the lifting station ; - Wheel frame for transporting the belt lifting station | R331: Longueur 1.150 mm ; Largeur 315 mm ; Hauteur de levage minimale 170 mm ; Hauteur de levage maximale 470 mm ; Poids 14,9 kg | U331: Height / Safe Lifting Capacity: ; 0 – 25 mm / 225 kg ; 25 – 50 mm / 450 kg ; 50 – 75 mm / 675 kg ; 75 – 100 mm / 900 kg ; 100 – 125 mm / 1.150 kg ; 125 – 150 mm / 1.350 kg ; 150 – 175 mm / 1.600 kg ; > 175 mm / 1.800 kg | W331: Gemaakt van lichtgewicht aluminium, gemakkelijk te vervoeren. ; Geschikt voor bandbreedtes van 650 mm tot 1.000 mm. | X331: Aus leichtem Aluminium, einfach zu transportieren. ; Geeignet für Bandbreiten von 650 mm bis 1.000 mm. | Y331: Made of lightweight aluminium, easy to transport. ; Suitable for belt width between 650 mm to 1.000 mm. ; It reduces risk for injury when lifting the conveyor belt when placing splicing station. ; A smart tool for quicker conveyor roller replacement. ; | Z331: Fabriqué en aluminium léger, facile à transporter. ; Convient pour une largeur de bande comprise entre 650 mm et 1 000 mm. | AG331: 083 | AH331: 091 | AI331: 031 | AJ331: Spann- u Hebewerkzeuge
A332: BELT-CLAMP-1500KG-NEWDESIGNKR | B332: BELT CLAMP 1500KG-NEW DESIGN | C332: 0,000 | D332: 34, Verbruikte materialen | E332: 17614, Krozmet s.c. | F332: Actief | G332: 110,000 | H332: 220 | I332: 05_Tools | J332: 05-04_REX-CLAMP | K332: T-REX Banden klem ; 1500 kg | L332: T-REX Gurtklemme ; 1500 kg | M332: T-REX Belt Clamp ; 1500 kg | N332: T-REX Pince ; 1500 kg | O332: Stevig ontwerp: 1.500 kg. ; > 6 mm Banddikte | P332: Verstärkte Ausführung: 1.500 kg. ; > 6 mm Gurt Stärke | Q332: Strong design: 1.500 kg. ; > 6 mm Belt Thickness ; Overall length ± 418 mm ; Height ± 235 mm ; Width ± 90 mm ; Safety shackle 3,25 T ; Weight approx. 6,740 kg | R332: Design avancé: 1.500 kg. ; > 6 mm Épaisseur de la bande | S332: Strippen transportband (verwijderen van rubber deklagen, inlagen/ staalkabels) ter voorbereiding van lasverbinding ; Samentrekken van uiteinden transportband voor snelle reparatie / montage | T332: Zum Entfernen von Gummi (Deckplatten und Textileinlagen) von Textilfördergurten (vorbereiten Gurtverbindung) ; Für das einziehen von Förderbänder | U332: Stripping conveyor belt (removal of rubber covers, fabric / steel cables) for splicing ; Pulling conveyor belts together for quick repair / installation | V332: Pour séparer les plis (caoutchouc et textile / câbles métalliques) avant jonction ; Pour rapprocher les extrémités de la bande transporteuse l’un vers l’autre pour réparation ou installation facile et rapide | AC332: Belt stripping & Belt pulling | AD332: Préparation des jonctions | AG332: 083 | AH332: 091 | AI332: 031 | AJ332: Spann- u Hebewerkzeuge
A333: BELT-CLAMP-800KG-NEWDESIGNKR | B333: BELT CLAMP 800KG-NEW DESIGN | C333: 0,000 | D333: 34, Verbruikte materialen | E333: 17614, Krozmet s.c. | F333: Actief | G333: 95,000 | H333: 190 | I333: 05_Tools | J333: 05-04_REX-CLAMP | K333: T-REX Banden klem ; 800 kg | L333: T-REX Gurtklemme ; 800 kg | M333: T-REX Belt Clamp ; 800 kg | N333: T-REX Pince ; 800 kg | O333: Stevig ontwerp: 800 kg. ; < 6 mm Band dikte | P333: Verstärkte Ausführung: 800 kg. ; < 6 mm Gurt Stärke | Q333: Strong design: 800 kg. ; < 6 mm Belt Thickness ; Overall length ± 315 mm ; Height ± 150 mm ; Width ± 98 mm ; Safety shackle 1,5 T ; Weight approx. 2,784 kg | R333: Design avancé: 800 kg. ; < 6 mm Épaisseur de la bande | S333: Strippen transportband (verwijderen van rubber deklagen, inlagen/ staalkabels) ter voorbereiding van lasverbinding ; Samentrekken van uiteinden transportband voor snelle reparatie / montage | T333: Zum Entfernen von Gummi (Deckplatten und Textileinlagen) von Textilfördergurten (vorbereiten Gurtverbindung) ; Für das einziehen von Förderbänder | U333: Stripping conveyor belt (removal of rubber covers, fabric / steel cables) for splicing ; Pulling conveyor belts together for quick repair / installation | V333: Pour séparer les plis (caoutchouc et textile / câbles métalliques) avant jonction ; Pour rapprocher les extrémités de la bande transporteuse l’un vers l’autre pour réparation ou installation facile et rapide | AC333: Belt stripping & Belt pulling | AD333: Préparation des jonctions | AG333: 083 | AH333: 091 | AI333: 031 | AJ333: Spann- u Hebewerkzeuge
A334: BEVESTIGINGSBANDEN-NYLON-APX | B334: Nylon bevestigingsbanden-kapnr. 1 t/m 9 | C334: 12,600 | D334: 21, Bandoverkappingen | E334: 16914, Phenix Industries | F334: Actief | G334: 9,810 | H334: 17 | I334: 12_Safety Products | J334: 12-02_Conveyor Belt Covers, Steel | K334: Nylon bevestigingsbanden-kapnr. 1+2+3 | L334: Nylon-Befestigungsriemen Hauben Nr. 1+2+3 | M334: Nylon Fixing Straps Cover No. 1+2+3 | N334: Sangles de fixation en nylon pour capot nr. 1+2+3 | AG334: 083 | AH334: 998 | AI334: 998 | AJ334: Industrie sonstiges
A335: BEVESTIGINGSBANDEN-NYLON-BPX | B335: Nylon bevestigingsbanden-kapnr. 4+5 | C335: 13,350 | D335: 21, Bandoverkappingen | E335: 16914, Phenix Industries | F335: Actief | G335: 10,350 | H335: 999 | I335: 12_Safety Products | J335: 12-02_Conveyor Belt Covers, Steel | K335: Nylon bevestigingsbanden-kapnr. 4+5 | L335: Nylon-Befestigungsriemen Hauben Nr. 4+5 | M335: Nylon Fixing Straps Cover No. 4+5 | N335: Sangles de fixation en nylon pour capot nr. 4+5 | AG335: 083 | AH335: 998 | AI335: 998 | AJ335: Industrie sonstiges
A336: BEVESTIGINGSBANDEN-NYLON-CPX | B336: Nylon bevestigingsbanden-kapnr. 6+7 | C336: 13,350 | D336: 21, Bandoverkappingen | E336: 16914, Phenix Industries | F336: Actief | G336: 10,840 | H336: 999 | I336: 12_Safety Products | J336: 12-02_Conveyor Belt Covers, Steel | K336: Nylon bevestigingsbanden-kapnr. 6+7 | L336: Nylon-Befestigungsriemen Hauben Nr. 6+7 | M336: Nylon Fixing Straps Cover No. 6+7 | N336: Sangles de fixation en nylon pour capot nr. 6+7 | AG336: 083 | AH336: 998 | AI336: 998 | AJ336: Industrie sonstiges
A337: BEVESTIGINGSBANDEN-RVS-1RO | B337: RVS bevestigingsbanden tbv kapnr. 1 | C337: 21,500 | D337: 21, Bandoverkappingen | E337: 12034, Renolit Ondex | F337: Actief | G337: 9,700 | H337: 999 | I337: 12_Safety Products | J337: 12-03_Conveyor Belt Covers, PVC | K337: RVS bevestigingsbanden tbv kapnr. 1 | L337: Edelstahl-Befestigungsriemen für Hauben-Nr. 1 | M337: Stainless steel fastening straps for cover nr. 1 | N337: Sangles de fixation en acier inoxydable pour capot nr. 1 | AG337: 083 | AH337: 998 | AI337: 998 | AJ337: Industrie sonstiges
A338: BEVESTIGINGSBANDEN-RVS-2RO | B338: RVS bevestigingsbanden tbv kapnr. 2 | C338: 21,500 | D338: 21, Bandoverkappingen | E338: 12034, Renolit Ondex | F338: Actief | G338: 9,700 | H338: 999 | I338: 12_Safety Products | J338: 12-03_Conveyor Belt Covers, PVC | K338: RVS bevestigingsbanden tbv kapnr. 2 | L338: Edelstahl-Befestigungsriemen für Hauben-Nr. 2 | M338: Stainless steel fastening straps for cover nr. 2 | N338: Sangles de fixation en acier inoxydable pour capot nr. 2 | AG338: 083 | AH338: 998 | AI338: 998 | AJ338: Industrie sonstiges
A339: BEVESTIGINGSBANDEN-RVS-3RO | B339: RVS bevestigingsbanden tbv kapnr. 3 | C339: 21,500 | D339: 21, Bandoverkappingen | E339: 12034, Renolit Ondex | F339: Actief | G339: 9,700 | H339: 999 | I339: 12_Safety Products | J339: 12-03_Conveyor Belt Covers, PVC | K339: RVS bevestigingsbanden tbv kapnr. 3 | L339: Edelstahl-Befestigungsriemen für Hauben-Nr. 3 | M339: Stainless steel fastening straps for cover nr. 3 | N339: Sangles de fixation en acier inoxydable pour capot nr. 3 | AG339: 083 | AH339: 998 | AI339: 998 | AJ339: Industrie sonstiges
...

Sheet Produktkategorien EN
A1: Hoofdcategorie | B1: Subcategorie | C1: Hoofdcategorie | D1: Subcategorie | E1: Hoofdcategorie | F1: Subcategorie | G1: Hoofdcategorie | H1: Subcategorie
A2: 01_Conveyor Belts | B2: 01-01_Anti Abrasion | C2: 01_Fördergurte | D2: 01-01_Abriebfest | E2: 01_Bandes transporteuses | F2: 01-01_Anti Abrasion | G2: 01_Transportbanden | H2: 01-01_Slijtbestendig
A3: 02_Profiled Conveyor Belts | B3: 01-02_Heat Resistant | C3: 02_Chevron Fördergurte | D3: 01-02_Hitzebeständig | E3: 02_Bandes transporteuses à Chevrons | F3: 01-02_Anti-chaleur | G3: 02_Transportbanden met profiel | H3: 01-02_Hittebestendig
A4: 03_Wear Protection | B4: 01-03_Oil and Grease Resistant | C4: 03_Verschleißschutz | D4: 01-03_Öl- und Fettbeständig | E4: 03_Protection anti-usure | F4: 01-03_Résistant aux huiles et graisses | G4: 03_Bescherming tegen slijtage | H4: 01-03_Olie- en vetbestendig
A5: 04_Drum Lagging | B5: 01-04_Bareback | C5: 04_Trommelbeläge | D5: 01-04_Gleitfördergurte | E5: 04_Garnissage pour tambour | F5: 01-04_Bandes sole de glisse | G5: 04_Trommelbekleding | H5: 01-04_Glijbanden
A6: 05_Tools | B6: 01-05_Ripstop | C6: 05_Werkzeuge | D6: 01-05_Ripstop | E6: 05_Outillage | F6: 01-05_Ripstop / Bande a breaker | G6: 05_Gereedschap | H6: 01-05_Ripstop
A7: 06_Vulcanization Materials | B7: 01-06_Supergrip Black | C7: 06_Vulkanisiermaterialen | D7: 01-06_Supergrip Schwarz | E7: 06_Matériaux de vulcanisation | F7: 01-06_Supergrip Noir | G7: 06_Vulkanisatiemateriaal | H7: 01-06_Supergrip Zwart
A8: 07_Repair Material | B8: 01-07_Supergrip Beige | C8: 07_Reparaturmaterial | D8: 01-07_Supergrip Beige | E8: 07_Matériaux de réparation | F8: 01-07_Supergrip Beige | G8: 07_Reparatiemateriaal | H8: 01-07_Supergrip Beige
A9: 08_Belt Cleaning | B9: 01-08_Elevator | C9: 08_Fördergurt-Reinigungssysteme | D9: 01-08_Elevator | E9: 08_Nettoyage bande transporteuse | F9: 01-08_Sangles élévatrices | G9: 08_Transportbandreiniging | H9: 01-08_Elevatorbanden
A10: 09_Components | B10: 01-09_Cross-Stable | C10: 09_Komponenten | D10: 01-09_Quersteif | E10: 09_Composants | F10: 01-09_Cross-Rigid | G10: 09_Componenten | H10: 01-09_Dwarsstabiel
A11: 10_Belt Tracking | B11: 01-10_T-Flex | C11: 10_Fördergurt-Zentrierung | D11: 01-10_T-Flex | E11: 10_Centrage de bande transporteuse | F11: 01-10_T-Flex | G11: 10_Transportbandstuursystemen | H11: 01-10_T-Flex
A12: 11_TQ Rollers | B12: 01-11_Saw Mill | C12: 11_TQ Rolle | D12: 01-11_Holz | E12: 11_TQ rouleaux | F12: 01-11_Bandes pour scieries | G12: 11_TQ Rollen | H12: 01-11_Saw Mill
A13: 12_Safety Products | B13: 01-12_Round Baler | C13: 12_Schutzvorrichtungen | D13: 01-12_Rundballenpresse | E13: 12_Produits de sécurité | F13: 01-12_Courroies Round Balers | G13: 12_Veiligheidsproducten | H13: 01-12_Round Baler
B14: 02-01_Profile height 6 – 13½ mm | D14: 02-01_Profilhöhe 6 – 13½ mm | F14: 02-01_Bandes à Chevrons, hauteur du profil 6 - 13½ mm | H14: 02-01_Profiel hoogte 6 – 13½ mm
B15: 02-02_Profile height 15 mm | D15: 02-02_Profilhöhe 15 mm | F15: 02-02_Bandes à Chevrons, hauteur du profil 15 mm | H15: 02-02_Profiel hoogte 15 mm
B16: 02-03_Profile height 17 mm | D16: 02-03_Profilhöhe 17 mm | F16: 02-03_Bandes à Chevrons, hauteur du profil 17 mm | H16: 02-03_Profiel hoogte 17 mm
B17: 02-04_Profile height 25 mm | D17: 02-04_Profilhöhe 25 mm | F17: 02-04_Bandes à Chevrons, hauteur du profil 25 mm | H17: 02-04_Profiel hoogte 25 mm
B18: 02-05_Profile height 32 mm | D18: 02-05_Profilhöhe 32 mm | F18: 02-05_Bandes à Chevrons, hauteur du profil 32 mm | H18: 02-05_Profiel hoogte 32 mm
B19: 02-06_Oil and Grease Resistant | D19: 02-06_ Öl und fettbeständig | F19: 02-06_Bandes à chevrons, résistant aux huiles et graisses | H19: 02-06_Olie- en vetbestendig
B20: 02-07_Salt | D20: 02-07_Salz | F20: 02-07_Bandes pour saleuses | H20: 02-07_Zoutbanden
B21: 03-01_T-REX40 with Bonding Layer | D21: 03-01_T-REX40 mit Kontaktschicht | F21: 03-01_T-REX40 avec face adhésive | H21: 03-01_T-REX40 met Lijmlaag
B22: 03-02_T-REX40 without Bonding Layer | D22: 03-02_T-REX40 ohne Kontaktschicht | F22: 03-02_T-REX40 sans face adhésive | H22: 03-02_T-REX40 zonder Lijmlaag
B23: 03-03_T-REX40 Side Skirt Rubber | D23: 03-03_T-REX40 Seitenführungsgummi | F23: 03-03_T-REX40 Bavettes | H23: 03-03_T-REX40 Zijgeleidingsrubber
B24: 03-04_T-REX50 with Bonding Layer | D24: 03-04_T-REX50 mit Kontaktschicht | F24: 03-04_T-REX50 avec face adhésive | H24: 03-04_T-REX50 met Lijmlaag
B25: 03-05_T-REX50 without Bonding Layer | D25: 03-05_T-REX50 ohne Kontaktschicht | F25: 03-05_T-REX50 sans face adhésive | H25: 03-05_T-REX50 zonder Lijmlaag
... B90: 12-04_Inspection Door + Screen | D90: 12-04_Inspektionstür + Fenster | F90: 12-04_Inspection par | H90: 12-04_Inspectiedeuren

Sheet INPUT MA
A1: Webshop laag 0 | B1: Code laag 1 | C1: Webshop laag 1 EN | D1: Webshop laag 1 NL | E1: Webshop laag 1 FR | F1: Webshop laag 1 DE | G1: Code laag 2 | H1: Webshop laag 2 EN | I1: Webshop laag 2 NL | J1: Webshop laag 2 FR | K1: Webshop laag 2 DE
B2: A | C2: 01_Conveyor Belts | D2: =IFERROR(VLOOKUP(C2,'Produktkategorien EN'!A:H,7,FALSE),"") -> 01_Transportbanden | E2: =IFERROR(VLOOKUP(C2,'Produktkategorien EN'!A:H,5,FALSE),"") -> 01_Bandes transporteuses | F2: =IFERROR(VLOOKUP(C2,'Produktkategorien EN'!A:H,3,FALSE),"") -> 01_Fördergurte | G2: A1 | H2: 01-01_Anti Abrasion | I2: 01-01_Slijtbestendig | J2: 01-01_Anti Abrasion | K2: 01-01_Abriebfest
B3: A | D3: =IFERROR(VLOOKUP(C3,'Produktkategorien EN'!A:H,7,FALSE),"") | E3: =IFERROR(VLOOKUP(C3,'Produktkategorien EN'!A:H,5,FALSE),"") | F3: =IFERROR(VLOOKUP(C3,'Produktkategorien EN'!A:H,3,FALSE),"") | G3: A2 | H3: 01-02_Heat Resistant | I3: 01-02_Hittebestendig | J3: 01-02_anti-chaleur | K3: 01-02_Hitzebeständig
B4: A | D4: =IFERROR(VLOOKUP(C4,'Produktkategorien EN'!A:H,7,FALSE),"") | E4: =IFERROR(VLOOKUP(C4,'Produktkategorien EN'!A:H,5,FALSE),"") | F4: =IFERROR(VLOOKUP(C4,'Produktkategorien EN'!A:H,3,FALSE),"") | G4: A3 | H4: 01-03_Oil and Grease Resistant | I4: 01-03_Olie- en vetbestendig | J4: 01-03_résistant aux huiles et graisses | K4: 01-03_Öl- und Fettbeständig
B5: A | D5: =IFERROR(VLOOKUP(C5,'Produktkategorien EN'!A:H,7,FALSE),"") | E5: =IFERROR(VLOOKUP(C5,'Produktkategorien EN'!A:H,5,FALSE),"") | F5: =IFERROR(VLOOKUP(C5,'Produktkategorien EN'!A:H,3,FALSE),"") | G5: A4 | H5: 01-04_Bareback | I5: 01-04_Glijbanden | J5: 01-04_Bandes glissantes | K5: 01-04_Gleitfördergurte
B6: A | D6: =IFERROR(VLOOKUP(C6,'Produktkategorien EN'!A:H,7,FALSE),"") | E6: =IFERROR(VLOOKUP(C6,'Produktkategorien EN'!A:H,5,FALSE),"") | F6: =IFERROR(VLOOKUP(C6,'Produktkategorien EN'!A:H,3,FALSE),"") | G6: A5 | H6: 01-05_Ripstop | I6: 01-05_Ripstop | J6: 01-05_Ripstop | K6: 01-05_Ripstop
B7: A | D7: =IFERROR(VLOOKUP(C7,'Produktkategorien EN'!A:H,7,FALSE),"") | E7: =IFERROR(VLOOKUP(C7,'Produktkategorien EN'!A:H,5,FALSE),"") | F7: =IFERROR(VLOOKUP(C7,'Produktkategorien EN'!A:H,3,FALSE),"") | G7: A6 | H7: 01-06_Supergrip Black | I7: 01-06_Supergrip Zwart | J7: 01-06_Supergrip Noir | K7: 01-06_Supergrip Schwarz
B8: A | D8: =IFERROR(VLOOKUP(C8,'Produktkategorien EN'!A:H,7,FALSE),"") | E8: =IFERROR(VLOOKUP(C8,'Produktkategorien EN'!A:H,5,FALSE),"") | F8: =IFERROR(VLOOKUP(C8,'Produktkategorien EN'!A:H,3,FALSE),"") | G8: A7 | H8: 01-07_Supergrip Beige | I8: 01-07_Supergrip Beige | J8: 01-07_Supergrip Beige | K8: 01-07_Supergrip Beige
B9: A | D9: =IFERROR(VLOOKUP(C9,'Produktkategorien EN'!A:H,7,FALSE),"") | E9: =IFERROR(VLOOKUP(C9,'Produktkategorien EN'!A:H,5,FALSE),"") | F9: =IFERROR(VLOOKUP(C9,'Produktkategorien EN'!A:H,3,FALSE),"") | G9: A8 | H9: 01-08_Elevator | I9: 01-08_Elevatorbanden | J9: 01-08_Sangles élévatrices | K9: 01-08_Elevator
B10: A | D10: =IFERROR(VLOOKUP(C10,'Produktkategorien EN'!A:H,7,FALSE),"") | E10: =IFERROR(VLOOKUP(C10,'Produktkategorien EN'!A:H,5,FALSE),"") | F10: =IFERROR(VLOOKUP(C10,'Produktkategorien EN'!A:H,3,FALSE),"") | G10: A9 | H10: 01-09_Cross-Stable | I10: 01-09_Dwarsstabiel | J10: 01-09_Cross-Rigid | K10: 01-09_Quersteif
B11: A | D11: =IFERROR(VLOOKUP(C11,'Produktkategorien EN'!A:H,7,FALSE),"") | E11: =IFERROR(VLOOKUP(C11,'Produktkategorien EN'!A:H,5,FALSE),"") | F11: =IFERROR(VLOOKUP(C11,'Produktkategorien EN'!A:H,3,FALSE),"") | G11: A10 | H11: 01-10_T-Flex | I11: 01-10_T-Flex | J11: 01-10_T-Flex | K11: 01-10_T-Flex
B12: A | D12: =IFERROR(VLOOKUP(C12,'Produktkategorien EN'!A:H,7,FALSE),"") | E12: =IFERROR(VLOOKUP(C12,'Produktkategorien EN'!A:H,5,FALSE),"") | F12: =IFERROR(VLOOKUP(C12,'Produktkategorien EN'!A:H,3,FALSE),"") | G12: A11 | H12: 01-11_Saw Mill | I12: 01-11_Saw Mill | J12: 01-11_Bandes pour scieries | K12: 01-11_Holz
B13: A | D13: =IFERROR(VLOOKUP(C13,'Produktkategorien EN'!A:H,7,FALSE),"") | E13: =IFERROR(VLOOKUP(C13,'Produktkategorien EN'!A:H,5,FALSE),"") | F13: =IFERROR(VLOOKUP(C13,'Produktkategorien EN'!A:H,3,FALSE),"") | G13: A12 | H13: 01-12_Round Baler | I13: 01-12_Round Baler | J13: 01-12_Courroies Round Balers | K13: 01-12_Rundballenpresse
B14: B | C14: 02_Profiled Conveyor Belts | D14: =IFERROR(VLOOKUP(C14,'Produktkategorien EN'!A:H,7,FALSE),"") -> 02_Transportbanden met profiel | E14: =IFERROR(VLOOKUP(C14,'Produktkategorien EN'!A:H,5,FALSE),"") -> 02_Bandes transporteuses à Chevrons | F14: =IFERROR(VLOOKUP(C14,'Produktkategorien EN'!A:H,3,FALSE),"") -> 02_Chevron Fördergurte | G14: B1 | H14: 02-01_Profile height 6 – 13½ mm | I14: 02-01_Profiel hoogte 6 – 13½ mm | J14: 02-01_Bandes à Chevrons, hauteur du profil 6 - 13½ mm | K14: 02-01_Profilhöhe 6 – 13½ mm
B15: B | D15: =IFERROR(VLOOKUP(C15,'Produktkategorien EN'!A:H,7,FALSE),"") | E15: =IFERROR(VLOOKUP(C15,'Produktkategorien EN'!A:H,5,FALSE),"") | F15: =IFERROR(VLOOKUP(C15,'Produktkategorien EN'!A:H,3,FALSE),"") | G15: B2 | H15: 02-02_Profile height 15 mm | I15: 02-02_Profiel hoogte 15 mm | J15: 02-02_Bandes à Chevrons, hauteur du profil 15 mm | K15: 02-02_Profilhöhe 15 mm
B16: B | D16: =IFERROR(VLOOKUP(C16,'Produktkategorien EN'!A:H,7,FALSE),"") | E16: =IFERROR(VLOOKUP(C16,'Produktkategorien EN'!A:H,5,FALSE),"") | F16: =IFERROR(VLOOKUP(C16,'Produktkategorien EN'!A:H,3,FALSE),"") | G16: B3 | H16: 02-03_Profile height 17 mm | I16: 02-03_Profiel hoogte 17 mm | J16: 02-03_Bandes à Chevrons, hauteur du profil 17 mm | K16: 02-03_Profilhöhe 17 mm
B17: B | D17: =IFERROR(VLOOKUP(C17,'Produktkategorien EN'!A:H,7,FALSE),"") | E17: =IFERROR(VLOOKUP(C17,'Produktkategorien EN'!A:H,5,FALSE),"") | F17: =IFERROR(VLOOKUP(C17,'Produktkategorien EN'!A:H,3,FALSE),"") | G17: B4 | H17: 02-04_Profile height 25 mm | I17: 02-04_Profiel hoogte 25 mm | J17: 02-04_Bandes à Chevrons, hauteur du profil 25 mm | K17: 02-04_Profilhöhe 25 mm
B18: B | D18: =IFERROR(VLOOKUP(C18,'Produktkategorien EN'!A:H,7,FALSE),"") | E18: =IFERROR(VLOOKUP(C18,'Produktkategorien EN'!A:H,5,FALSE),"") | F18: =IFERROR(VLOOKUP(C18,'Produktkategorien EN'!A:H,3,FALSE),"") | G18: B5 | H18: 02-05_Profile height 32 mm | I18: 02-05_Profiel hoogte 32 mm | J18: 02-05_Bandes à Chevrons, hauteur du profil 32 mm | K18: 02-05_Profilhöhe 32 mm
B19: B | D19: =IFERROR(VLOOKUP(C19,'Produktkategorien EN'!A:H,7,FALSE),"") | E19: =IFERROR(VLOOKUP(C19,'Produktkategorien EN'!A:H,5,FALSE),"") | F19: =IFERROR(VLOOKUP(C19,'Produktkategorien EN'!A:H,3,FALSE),"") | G19: B6 | H19: 02-06_Oil and Grease Resistant | I19: 02-06_Olie- en vetbestendig | J19: 02-06_Bandes à chevrons, résistant aux huiles et graisses | K19: 02-06_ Öl und fettbeständig
B20: B | D20: =IFERROR(VLOOKUP(C20,'Produktkategorien EN'!A:H,7,FALSE),"") | E20: =IFERROR(VLOOKUP(C20,'Produktkategorien EN'!A:H,5,FALSE),"") | F20: =IFERROR(VLOOKUP(C20,'Produktkategorien EN'!A:H,3,FALSE),"") | G20: B7 | H20: 02-07_Salt | I20: 02-07_Zoutbanden | J20: 02-07_Bandes pour saleuses | K20: 02-07_Salz
B21: C | C21: 03_Wear Protection | D21: =IFERROR(VLOOKUP(C21,'Produktkategorien EN'!A:H,7,FALSE),"") -> 03_Bescherming tegen slijtage | E21: =IFERROR(VLOOKUP(C21,'Produktkategorien EN'!A:H,5,FALSE),"") -> 03_Protection anti-usure | F21: =IFERROR(VLOOKUP(C21,'Produktkategorien EN'!A:H,3,FALSE),"") -> 03_Verschleißschutz | G21: C1 | H21: 03-01_T-REX40 with Bonding Layer | I21: 03-01_T-REX40 met Lijmlaag | J21: 03-01_T-REX40 avec face adhésive | K21: 03-01_T-REX40 mit Kontaktschicht
B22: C | D22: =IFERROR(VLOOKUP(C22,'Produktkategorien EN'!A:H,7,FALSE),"") | E22: =IFERROR(VLOOKUP(C22,'Produktkategorien EN'!A:H,5,FALSE),"") | F22: =IFERROR(VLOOKUP(C22,'Produktkategorien EN'!A:H,3,FALSE),"") | G22: C2 | H22: 03-02_T-REX40 without Bonding Layer | I22: 03-02_T-REX40 zonder Lijmlaag | J22: 03-02_T-REX40 sans face adhésive | K22: 03-02_T-REX40 ohne Kontaktschicht
B23: C | D23: =IFERROR(VLOOKUP(C23,'Produktkategorien EN'!A:H,7,FALSE),"") | E23: =IFERROR(VLOOKUP(C23,'Produktkategorien EN'!A:H,5,FALSE),"") | F23: =IFERROR(VLOOKUP(C23,'Produktkategorien EN'!A:H,3,FALSE),"") | G23: C3 | H23: 03-03_T-REX40 Side Skirt Rubber | I23: 03-03_T-REX40 Zijgeleidingsrubber | J23: 03-03_T-REX40 Bavettes | K23: 03-03_T-REX40 Seitenführungsgummi
B24: C | D24: =IFERROR(VLOOKUP(C24,'Produktkategorien EN'!A:H,7,FALSE),"") | E24: =IFERROR(VLOOKUP(C24,'Produktkategorien EN'!A:H,5,FALSE),"") | F24: =IFERROR(VLOOKUP(C24,'Produktkategorien EN'!A:H,3,FALSE),"") | G24: C4 | H24: 03-04_T-REX50 with Bonding Layer | I24: 03-04_T-REX50 met Lijmlaag | J24: 03-04_T-REX50 avec face adhésive | K24: 03-04_T-REX50 mit Kontaktschicht
B25: C | D25: =IFERROR(VLOOKUP(C25,'Produktkategorien EN'!A:H,7,FALSE),"") | E25: =IFERROR(VLOOKUP(C25,'Produktkategorien EN'!A:H,5,FALSE),"") | F25: =IFERROR(VLOOKUP(C25,'Produktkategorien EN'!A:H,3,FALSE),"") | G25: C5 | H25: 03-05_T-REX50 without Bonding Layer | I25: 03-05_T-REX50 zonder Lijmlaag | J25: 03-05_T-REX50 sans face adhésive | K25: 03-05_T-REX50 ohne Kontaktschicht
B26: C | D26: =IFERROR(VLOOKUP(C26,'Produktkategorien EN'!A:H,7,FALSE),"") | E26: =IFERROR(VLOOKUP(C26,'Produktkategorien EN'!A:H,5,FALSE),"") | F26: =IFERROR(VLOOKUP(C26,'Produktkategorien EN'!A:H,3,FALSE),"") | G26: C6 | H26: 03-06_T-REX50 Side Skirt Rubber | I26: 03-06_T-REX50 Zijgeleidingsrubber | J26: 03-06_T-REX50 Bavettes | K26: 03-06_T-REX50 Seitenführungsgummi
B27: C | D27: =IFERROR(VLOOKUP(C27,'Produktkategorien EN'!A:H,7,FALSE),"") | E27: =IFERROR(VLOOKUP(C27,'Produktkategorien EN'!A:H,5,FALSE),"") | F27: =IFERROR(VLOOKUP(C27,'Produktkategorien EN'!A:H,3,FALSE),"") | G27: C7 | H27: 03-07_T-REX60 with Bonding Layer | I27: 03-07_T-REX60 met Lijmlaag | J27: 03-07_T-REX60 avec face adhésive | K27: 03-07_T-REX60 mit Kontaktschicht
B28: C | D28: =IFERROR(VLOOKUP(C28,'Produktkategorien EN'!A:H,7,FALSE),"") | E28: =IFERROR(VLOOKUP(C28,'Produktkategorien EN'!A:H,5,FALSE),"") | F28: =IFERROR(VLOOKUP(C28,'Produktkategorien EN'!A:H,3,FALSE),"") | G28: C8 | H28: 03-08_T-REX60 without Bonding Layer | I28: 03-08_T-REX60 zonder Lijmlaag | J28: 03-08_T-REX60 sans face adhésive | K28: 03-08_T-REX60 ohne Kontaktschicht
B29: C | D29: =IFERROR(VLOOKUP(C29,'Produktkategorien EN'!A:H,7,FALSE),"") | E29: =IFERROR(VLOOKUP(C29,'Produktkategorien EN'!A:H,5,FALSE),"") | F29: =IFERROR(VLOOKUP(C29,'Produktkategorien EN'!A:H,3,FALSE),"") | G29: C9 | H29: 03-09_T-REX60 Side Skirt Rubber | I29: 03-09_T-REX60 Zijgeleidingsrubber | J29: 03-09_T-REX60 Bavettes | K29: 03-09_T-REX60 Seitenführungsgummi
B30: C | D30: =IFERROR(VLOOKUP(C30,'Produktkategorien EN'!A:H,7,FALSE),"") | E30: =IFERROR(VLOOKUP(C30,'Produktkategorien EN'!A:H,5,FALSE),"") | F30: =IFERROR(VLOOKUP(C30,'Produktkategorien EN'!A:H,3,FALSE),"") | G30: C10 | H30: 03-10_LINA-REX | I30: 03-10_LINA-REX | J30: 03-10_LINA-REX | K30: 03-10_LINA-REX
B31: C | D31: =IFERROR(VLOOKUP(C31,'Produktkategorien EN'!A:H,7,FALSE),"") | E31: =IFERROR(VLOOKUP(C31,'Produktkategorien EN'!A:H,5,FALSE),"") | F31: =IFERROR(VLOOKUP(C31,'Produktkategorien EN'!A:H,3,FALSE),"") | G31: C11 | H31: 03-11_Caramel | I31: 03-11_Karamel | J31: 03-11_Caramel | K31: 03-11_Karamel
B32: C | D32: =IFERROR(VLOOKUP(C32,'Produktkategorien EN'!A:H,7,FALSE),"") | E32: =IFERROR(VLOOKUP(C32,'Produktkategorien EN'!A:H,5,FALSE),"") | F32: =IFERROR(VLOOKUP(C32,'Produktkategorien EN'!A:H,3,FALSE),"") | G32: C12 | H32: 03-12_Economy Rubber Sheets | I32: 03-12_Economy Slijtvast | J32: 03-12_Economy Caoutchouc | K32: 03-12_Economy gummiplatten
B33: D | C33: 04_Drum Lagging | D33: =IFERROR(VLOOKUP(C33,'Produktkategorien EN'!A:H,7,FALSE),"") -> 04_Trommelbekleding | E33: =IFERROR(VLOOKUP(C33,'Produktkategorien EN'!A:H,5,FALSE),"") -> 04_Garnissage pour tambour | F33: =IFERROR(VLOOKUP(C33,'Produktkategorien EN'!A:H,3,FALSE),"") -> 04_Trommelbeläge | G33: D1 | H33: 04-01_Mini Diamond Black | I33: 04-01_Mini Diamond Zwart | J33: 04-01_Mini Losange noir | K33: 04-01_Mini Raute Schwarz
B34: D | D34: =IFERROR(VLOOKUP(C34,'Produktkategorien EN'!A:H,7,FALSE),"") | E34: =IFERROR(VLOOKUP(C34,'Produktkategorien EN'!A:H,5,FALSE),"") | F34: =IFERROR(VLOOKUP(C34,'Produktkategorien EN'!A:H,3,FALSE),"") | G34: D2 | H34: 04-02_Mini Diamond Black Oil Resistant | I34: 04-02_Mini Diamond Zwart olie- en vetbestendig | J34: 04-02_Mini Losange noir, résistant aux huiles et graisses | K34: 04-02_Mini Raute Schwarz Öl und Fettbeständig
B35: D | D35: =IFERROR(VLOOKUP(C35,'Produktkategorien EN'!A:H,7,FALSE),"") | E35: =IFERROR(VLOOKUP(C35,'Produktkategorien EN'!A:H,5,FALSE),"") | F35: =IFERROR(VLOOKUP(C35,'Produktkategorien EN'!A:H,3,FALSE),"") | G35: D3 | H35: 04-03_Maxi Diamond Black | I35: 04-03_Maxi Diamond Zwart | J35: 04-03_Maxi Losange noir | K35: 04-03_Maxi Raute Schwarz
B36: D | D36: =IFERROR(VLOOKUP(C36,'Produktkategorien EN'!A:H,7,FALSE),"") | E36: =IFERROR(VLOOKUP(C36,'Produktkategorien EN'!A:H,5,FALSE),"") | F36: =IFERROR(VLOOKUP(C36,'Produktkategorien EN'!A:H,3,FALSE),"") | G36: D4 | H36: 04-04_Mini Diamond Red | I36: 04-04_Mini Diamond Rood | J36: 04-04_Mini Losange rouge | K36: 04-04_Mini Raute Rot
B37: D | D37: =IFERROR(VLOOKUP(C37,'Produktkategorien EN'!A:H,7,FALSE),"") | E37: =IFERROR(VLOOKUP(C37,'Produktkategorien EN'!A:H,5,FALSE),"") | F37: =IFERROR(VLOOKUP(C37,'Produktkategorien EN'!A:H,3,FALSE),"") | G37: D5 | H37: 04-05_Mini Diamond Blue | I37: 04-05_Mini Diamond Blauw | J37: 04-05_Mini Losange bleu | K37: 04-05_Mini Raute Blau
B38: D | D38: =IFERROR(VLOOKUP(C38,'Produktkategorien EN'!A:H,7,FALSE),"") | E38: =IFERROR(VLOOKUP(C38,'Produktkategorien EN'!A:H,5,FALSE),"") | F38: =IFERROR(VLOOKUP(C38,'Produktkategorien EN'!A:H,3,FALSE),"") | G38: D6 | H38: 04-06_Mini Diamond White | I38: 04-06_Mini Diamond Wit | J38: 04-06_Mini Losange blanc | K38: 04-06_Mini Raute Weiß
B39: D | D39: =IFERROR(VLOOKUP(C39,'Produktkategorien EN'!A:H,7,FALSE),"") | E39: =IFERROR(VLOOKUP(C39,'Produktkategorien EN'!A:H,5,FALSE),"") | F39: =IFERROR(VLOOKUP(C39,'Produktkategorien EN'!A:H,3,FALSE),"") | G39: D7 | H39: 04-07_Grooved White | I39: 04-07_Dwarsrib | J39: 04-07_Rainuré blanc | K39: 04-07_ Querrillen Profil Weiβ
B40: D | D40: =IFERROR(VLOOKUP(C40,'Produktkategorien EN'!A:H,7,FALSE),"") | E40: =IFERROR(VLOOKUP(C40,'Produktkategorien EN'!A:H,5,FALSE),"") | F40: =IFERROR(VLOOKUP(C40,'Produktkategorien EN'!A:H,3,FALSE),"") | G40: D8 | H40: 04-08_Rough Top | I40: 04-08_Rough Top | J40: 04-08_Rough Top | K40: 04-08_Rough Top
B41: D | D41: =IFERROR(VLOOKUP(C41,'Produktkategorien EN'!A:H,7,FALSE),"") | E41: =IFERROR(VLOOKUP(C41,'Produktkategorien EN'!A:H,5,FALSE),"") | F41: =IFERROR(VLOOKUP(C41,'Produktkategorien EN'!A:H,3,FALSE),"") | G41: D9 | H41: 04-09_Ceramic in Rubber CERA-REX | I41: 04-09_Keramiek in Rubber CERA-REX | J41: 04-09_Céramique en caoutchouc CERA-REX | K41: 04-09_Keramik in Gummi CERA-REX
B42: D | D42: =IFERROR(VLOOKUP(C42,'Produktkategorien EN'!A:H,7,FALSE),"") | E42: =IFERROR(VLOOKUP(C42,'Produktkategorien EN'!A:H,5,FALSE),"") | F42: =IFERROR(VLOOKUP(C42,'Produktkategorien EN'!A:H,3,FALSE),"") | G42: D10 | H42: 04-10_Ceramic in Rubber CERA-GUM | I42: 04-10_Keramiek in Rubber CERA-GUM | J42: 04-10_Céramique en caoutchouc CERA-GUM | K42: 04-10_Keramik in Gummi CERA-GUM
B43: D | D43: =IFERROR(VLOOKUP(C43,'Produktkategorien EN'!A:H,7,FALSE),"") | E43: =IFERROR(VLOOKUP(C43,'Produktkategorien EN'!A:H,5,FALSE),"") | F43: =IFERROR(VLOOKUP(C43,'Produktkategorien EN'!A:H,3,FALSE),"") | G43: D11 | H43: 04-11_REX-DRIVE | I43: 04-11_REX-DRIVE | J43: 04-11_REX-DRIVE | K43: 04-11_REX-DRIVE
B44: D | D44: =IFERROR(VLOOKUP(C44,'Produktkategorien EN'!A:H,7,FALSE),"") | E44: =IFERROR(VLOOKUP(C44,'Produktkategorien EN'!A:H,5,FALSE),"") | F44: =IFERROR(VLOOKUP(C44,'Produktkategorien EN'!A:H,3,FALSE),"") | G44: D12 | H44: 04-12_Mini Square Black | I44: 04-12_Mini Vierkant Zwart | J44: 04-12_Mini carré noir | K44: 04-12_Mini Quadrat Schwarz
B45: E | C45: 05_Tools | D45: =IFERROR(VLOOKUP(C45,'Produktkategorien EN'!A:H,7,FALSE),"") -> 05_Gereedschap | E45: =IFERROR(VLOOKUP(C45,'Produktkategorien EN'!A:H,5,FALSE),"") -> 05_Outillage | F45: =IFERROR(VLOOKUP(C45,'Produktkategorien EN'!A:H,3,FALSE),"") -> 05_Werkzeuge | G45: E1 | H45: 05-01_T-Rex Belt Lifting Station | I45: 05-01_T-Rex Belt Lifting Station | J45: 05-01_T-Rex station de levage de bande | K45: 05-01_T-Rex Bandhebeanlage
B46: E | D46: =IFERROR(VLOOKUP(C46,'Produktkategorien EN'!A:H,7,FALSE),"") | E46: =IFERROR(VLOOKUP(C46,'Produktkategorien EN'!A:H,5,FALSE),"") | F46: =IFERROR(VLOOKUP(C46,'Produktkategorien EN'!A:H,3,FALSE),"") | G46: E2 | H46: 05-02_Hand Tools | I46: 05-02_Hand gereedschap | J46: 05-02_Outillage de vulcanisation et de réparation | K46: 05-02_Handwerkzeuge
B47: E | D47: =IFERROR(VLOOKUP(C47,'Produktkategorien EN'!A:H,7,FALSE),"") | E47: =IFERROR(VLOOKUP(C47,'Produktkategorien EN'!A:H,5,FALSE),"") | F47: =IFERROR(VLOOKUP(C47,'Produktkategorien EN'!A:H,3,FALSE),"") | G47: E3 | H47: 05-03_Buffing Tools | I47: 05-03_Opruw gereedschap | J47: 05-03_Outils de ponçage | K47: 05-03_Rauwerkzeuge
B48: E | D48: =IFERROR(VLOOKUP(C48,'Produktkategorien EN'!A:H,7,FALSE),"") | E48: =IFERROR(VLOOKUP(C48,'Produktkategorien EN'!A:H,5,FALSE),"") | F48: =IFERROR(VLOOKUP(C48,'Produktkategorien EN'!A:H,3,FALSE),"") | G48: E4 | H48: 05-04_REX-CLAMP | I48: 05-04_REX-CLAMP | J48: 05-04_REX-Pince | K48: 05-04_REX-CLAMP Gurtklemme
B49: E | D49: =IFERROR(VLOOKUP(C49,'Produktkategorien EN'!A:H,7,FALSE),"") | E49: =IFERROR(VLOOKUP(C49,'Produktkategorien EN'!A:H,5,FALSE),"") | F49: =IFERROR(VLOOKUP(C49,'Produktkategorien EN'!A:H,3,FALSE),"") | G49: E5 | H49: 05-05_T-Rex Cold Splice Roller | I49: 05-05_T-Rex Aanroller (koude las) | J49: 05-05_T-REX Rouleur à double pression | K49: 05-05_T-Rex Anroller
B50: F | C50: 06_Vulcanization Materials | D50: =IFERROR(VLOOKUP(C50,'Produktkategorien EN'!A:H,7,FALSE),"") -> 06_Vulkanisatiemateriaal | E50: =IFERROR(VLOOKUP(C50,'Produktkategorien EN'!A:H,5,FALSE),"") -> 06_Matériaux de vulcanisation | F50: =IFERROR(VLOOKUP(C50,'Produktkategorien EN'!A:H,3,FALSE),"") -> 06_Vulkanisiermaterialen | G50: F1 | H50: 06-01_T-Rex Cleaner | I50: 06-01_T-Rex Cleaner | J50: 06-01_T-Rex Nettoyant | K50: 06-01_T-Rex Reinigungsmittel
B51: F | D51: =IFERROR(VLOOKUP(C51,'Produktkategorien EN'!A:H,7,FALSE),"") | E51: =IFERROR(VLOOKUP(C51,'Produktkategorien EN'!A:H,5,FALSE),"") | F51: =IFERROR(VLOOKUP(C51,'Produktkategorien EN'!A:H,3,FALSE),"") | G51: F2 | H51: 06-02_T-Rex Primer | I51: 06-02_T-Rex Primer | J51: 06-02_T-Rex Primer | K51: 06-02_T-Rex Primer
B52: F | D52: =IFERROR(VLOOKUP(C52,'Produktkategorien EN'!A:H,7,FALSE),"") | E52: =IFERROR(VLOOKUP(C52,'Produktkategorien EN'!A:H,5,FALSE),"") | F52: =IFERROR(VLOOKUP(C52,'Produktkategorien EN'!A:H,3,FALSE),"") | G52: F3 | H52: 06-03_T-Rex Glue for Cold Vulcanization | I52: 06-03_T-Rex lijm voor koudvulkanisatie | J52: 06-03_T-REX Colle pour vulcanisation à froid | K52: 06-03_T-Rex Kleber für Kaltvulkanisation
B53: F | D53: =IFERROR(VLOOKUP(C53,'Produktkategorien EN'!A:H,7,FALSE),"") | E53: =IFERROR(VLOOKUP(C53,'Produktkategorien EN'!A:H,5,FALSE),"") | F53: =IFERROR(VLOOKUP(C53,'Produktkategorien EN'!A:H,3,FALSE),"") | G53: F4 | H53: 06-04_T-Rex Glue for Hot Vulcanization | I53: 06-04_T-Rex lijm voor warmvulkanisatie | J53: 06-04_T-REX Colle pour vulcanisation à chaud | K53: 06-04_T-Rex Kleber für Heißverbindung
B54: F | D54: =IFERROR(VLOOKUP(C54,'Produktkategorien EN'!A:H,7,FALSE),"") | E54: =IFERROR(VLOOKUP(C54,'Produktkategorien EN'!A:H,5,FALSE),"") | F54: =IFERROR(VLOOKUP(C54,'Produktkategorien EN'!A:H,3,FALSE),"") | G54: F5 | H54: 06-05_Unvulcanized Cover Rubber | I54: 06-05_Ongevulkaniseerd dekrubber | J54: 06-05_Gomme de revêtement | K54: 06-05_Unvulkanisertes Deckgummi
B55: F | D55: =IFERROR(VLOOKUP(C55,'Produktkategorien EN'!A:H,7,FALSE),"") | E55: =IFERROR(VLOOKUP(C55,'Produktkategorien EN'!A:H,5,FALSE),"") | F55: =IFERROR(VLOOKUP(C55,'Produktkategorien EN'!A:H,3,FALSE),"") | G55: F6 | H55: 06-06_Unvulcanized Skim Rubber | I55: 06-06_Ongevulkaniseerd Tussenrubber | J55: 06-06_Gomme de liaison (skim) | K55: 06-06_Unvulkanisertes Zwischengummi
B56: G | C56: 07_Repair Material | D56: =IFERROR(VLOOKUP(C56,'Produktkategorien EN'!A:H,7,FALSE),"") -> 07_Reparatiemateriaal | E56: =IFERROR(VLOOKUP(C56,'Produktkategorien EN'!A:H,5,FALSE),"") -> 07_Matériaux de réparation | F56: =IFERROR(VLOOKUP(C56,'Produktkategorien EN'!A:H,3,FALSE),"") -> 07_Reparaturmaterial | G56: G1 | H56: 07-01_T-Rex Screw Splice | I56: 07-01_T-Rex Screw Splice | J56: 07-01_T-Rex Screw Splice | K56: 07-01_T-Rex Screw Splice
B57: G | D57: =IFERROR(VLOOKUP(C57,'Produktkategorien EN'!A:H,7,FALSE),"") | E57: =IFERROR(VLOOKUP(C57,'Produktkategorien EN'!A:H,5,FALSE),"") | F57: =IFERROR(VLOOKUP(C57,'Produktkategorien EN'!A:H,3,FALSE),"") | G57: G2 | H57: 07-02_Fourthane | I57: 07-02_Fourthane | J57: 07-02_Fourthane | K57: 07-02_Fourthane
B58: G | D58: =IFERROR(VLOOKUP(C58,'Produktkategorien EN'!A:H,7,FALSE),"") | E58: =IFERROR(VLOOKUP(C58,'Produktkategorien EN'!A:H,5,FALSE),"") | F58: =IFERROR(VLOOKUP(C58,'Produktkategorien EN'!A:H,3,FALSE),"") | G58: G3 | H58: 07-03_PERMA-FLEX | I58: 07-03_PERMA-FLEX | J58: 07-03_PERMA-FLEX | K58: 07-03_PERMA-FLEX
B59: G | D59: =IFERROR(VLOOKUP(C59,'Produktkategorien EN'!A:H,7,FALSE),"") | E59: =IFERROR(VLOOKUP(C59,'Produktkategorien EN'!A:H,5,FALSE),"") | F59: =IFERROR(VLOOKUP(C59,'Produktkategorien EN'!A:H,3,FALSE),"") | G59: G4 | H59: 07-04_T-Rex Repair Patches | I59: 07-04_T-Rex Reparatiepleisters | J59: 07-04_T-Rex Rustines | K59: 07-04_T-Rex Reparatur Flicken
B60: G | D60: =IFERROR(VLOOKUP(C60,'Produktkategorien EN'!A:H,7,FALSE),"") | E60: =IFERROR(VLOOKUP(C60,'Produktkategorien EN'!A:H,5,FALSE),"") | F60: =IFERROR(VLOOKUP(C60,'Produktkategorien EN'!A:H,3,FALSE),"") | G60: G5 | H60: 07-05_T-Rex Repair Strips | I60: 07-05_T-Rex Reparatiestroken | J60: 07-05_T-Rex Bande de réparation | K60: 07-05_T-Rex Reparatur Streifen
B61: G | D61: =IFERROR(VLOOKUP(C61,'Produktkategorien EN'!A:H,7,FALSE),"") | E61: =IFERROR(VLOOKUP(C61,'Produktkategorien EN'!A:H,5,FALSE),"") | F61: =IFERROR(VLOOKUP(C61,'Produktkategorien EN'!A:H,3,FALSE),"") | G61: G6 | H61: 07-06_Staples for Quick Repair | I61: 07-06_Bandkrammen voor snelle reparatie | J61: 07-06_Agrafes à crampons | K61: 07-06_Sechszack-Klammer
B62: G | D62: =IFERROR(VLOOKUP(C62,'Produktkategorien EN'!A:H,7,FALSE),"") | E62: =IFERROR(VLOOKUP(C62,'Produktkategorien EN'!A:H,5,FALSE),"") | F62: =IFERROR(VLOOKUP(C62,'Produktkategorien EN'!A:H,3,FALSE),"") | G62: G7 | H62: 07-07_Fasteners | I62: 07-07_Verbinders | J62: 07-07_Agrafes à plaques boulonnées | K62: 07-07_Gurtverbinder
B63: H | C63: 08_Belt Cleaning | D63: =IFERROR(VLOOKUP(C63,'Produktkategorien EN'!A:H,7,FALSE),"") -> 08_Transportbandreiniging | E63: =IFERROR(VLOOKUP(C63,'Produktkategorien EN'!A:H,5,FALSE),"") -> 08_Nettoyage bande transporteuse | F63: =IFERROR(VLOOKUP(C63,'Produktkategorien EN'!A:H,3,FALSE),"") -> 08_Fördergurt-Reinigungssysteme | G63: H1 | H63: 08-01_Scraper Rubber | I63: 08-01_Afschraaprubber | J63: 08-01_Caoutchouc pour racleur | K63: 08-01_Abstreifgummi
B64: H | D64: =IFERROR(VLOOKUP(C64,'Produktkategorien EN'!A:H,7,FALSE),"") | E64: =IFERROR(VLOOKUP(C64,'Produktkategorien EN'!A:H,5,FALSE),"") | F64: =IFERROR(VLOOKUP(C64,'Produktkategorien EN'!A:H,3,FALSE),"") | G64: H2 | H64: 08-02_V-Return Scraper (Black-Red-Black) | I64: 08-02_V-Ploeg schraper (zwart-rood-zwart) | J64: 08-02_V-Retour Racleur (Noir-Rouge-Noir) | K64: 08-02_V-Retour Abstreifer (Schwarz-Rot-Schwarz)
B65: H | D65: =IFERROR(VLOOKUP(C65,'Produktkategorien EN'!A:H,7,FALSE),"") | E65: =IFERROR(VLOOKUP(C65,'Produktkategorien EN'!A:H,5,FALSE),"") | F65: =IFERROR(VLOOKUP(C65,'Produktkategorien EN'!A:H,3,FALSE),"") | G65: H3 | H65: 08-03_T-Rex PUR Scraper | I65: 08-03_T-Rex PUR Schraper | J65: 08-03_T-Rex PUR Racleur | K65: 08-03_T-REX PUR Abstreifer
B66: H | D66: =IFERROR(VLOOKUP(C66,'Produktkategorien EN'!A:H,7,FALSE),"") | E66: =IFERROR(VLOOKUP(C66,'Produktkategorien EN'!A:H,5,FALSE),"") | F66: =IFERROR(VLOOKUP(C66,'Produktkategorien EN'!A:H,3,FALSE),"") | G66: H4 | H66: 08-04_FTK-REX Secondary Scraper | I66: 08-04_FTK-REX Secondaire Schraper | J66: 08-04_FTK-REX Racleur secondaire | K66: 08-04_FTK-REX Sekundäre Abstreifer
B67: H | D67: =IFERROR(VLOOKUP(C67,'Produktkategorien EN'!A:H,7,FALSE),"") | E67: =IFERROR(VLOOKUP(C67,'Produktkategorien EN'!A:H,5,FALSE),"") | F67: =IFERROR(VLOOKUP(C67,'Produktkategorien EN'!A:H,3,FALSE),"") | G67: H5 | H67: 08-05_Belt Brush Mat | I67: 08-05_Egelmatten | J67: 08-05_Tapis de brosse à bande | K67: 08-05_Noppenmatte
B68: I | C68: 09_Components | D68: =IFERROR(VLOOKUP(C68,'Produktkategorien EN'!A:H,7,FALSE),"") -> 09_Componenten | E68: =IFERROR(VLOOKUP(C68,'Produktkategorien EN'!A:H,5,FALSE),"") -> 09_Composants | F68: =IFERROR(VLOOKUP(C68,'Produktkategorien EN'!A:H,3,FALSE),"") -> 09_Komponenten | G68: I1 | H68: 09-01_Cleats | I68: 09-01_Meenemers | J68: 09-01_Tasseaux | K68: 09-01_Stollen
B69: I | D69: =IFERROR(VLOOKUP(C69,'Produktkategorien EN'!A:H,7,FALSE),"") | E69: =IFERROR(VLOOKUP(C69,'Produktkategorien EN'!A:H,5,FALSE),"") | F69: =IFERROR(VLOOKUP(C69,'Produktkategorien EN'!A:H,3,FALSE),"") | G69: I2 | H69: 09-02_Sidewalls | I69: 09-02_Golfrand | J69: 09-02_Bords de contenance ondulés | K69: 09-02_Wellenkanten
B70: I | D70: =IFERROR(VLOOKUP(C70,'Produktkategorien EN'!A:H,7,FALSE),"") | E70: =IFERROR(VLOOKUP(C70,'Produktkategorien EN'!A:H,5,FALSE),"") | F70: =IFERROR(VLOOKUP(C70,'Produktkategorien EN'!A:H,3,FALSE),"") | G70: I3 | H70: 09-03_V-Profiles | I70: 09-03_Stuursnaren | J70: 09-03_Profil en V | K70: 09-03_V-Profil
B71: I | D71: =IFERROR(VLOOKUP(C71,'Produktkategorien EN'!A:H,7,FALSE),"") | E71: =IFERROR(VLOOKUP(C71,'Produktkategorien EN'!A:H,5,FALSE),"") | F71: =IFERROR(VLOOKUP(C71,'Produktkategorien EN'!A:H,3,FALSE),"") | G71: I4 | H71: 09-04_Skirting Block | I71: 09-04_Zijgeleidings blok | J71: 09-04_Bloc d’étanchéité | K71: 09-04_Skirting Block
B72: I | D72: =IFERROR(VLOOKUP(C72,'Produktkategorien EN'!A:H,7,FALSE),"") | E72: =IFERROR(VLOOKUP(C72,'Produktkategorien EN'!A:H,5,FALSE),"") | F72: =IFERROR(VLOOKUP(C72,'Produktkategorien EN'!A:H,3,FALSE),"") | G72: I5 | H72: 09-05_Impact & Glide Bars | I72: 09-05_Impact & Glide Bars | J72: 09-05_Barre d’impact et de glissement | K72: 09-05_Schlagabsorber und Gleit Balken
B73: I | D73: =IFERROR(VLOOKUP(C73,'Produktkategorien EN'!A:H,7,FALSE),"") | E73: =IFERROR(VLOOKUP(C73,'Produktkategorien EN'!A:H,5,FALSE),"") | F73: =IFERROR(VLOOKUP(C73,'Produktkategorien EN'!A:H,3,FALSE),"") | G73: I6 | H73: 09-06_Polyurethane Blue, Impact Plate V | I73: 09-06_Polyurethaan Blauw, Impact plaat V | J73: 09-06_Plaque d’impact profil en « V » | K73: 09-06_Schlagabsorber Platte V Profil, Polyurethan Blau
B74: I | D74: =IFERROR(VLOOKUP(C74,'Produktkategorien EN'!A:H,7,FALSE),"") | E74: =IFERROR(VLOOKUP(C74,'Produktkategorien EN'!A:H,5,FALSE),"") | F74: =IFERROR(VLOOKUP(C74,'Produktkategorien EN'!A:H,3,FALSE),"") | G74: I7 | H74: 09-07_Polyurethane Blue, Impact Plate Z | I74: 09-07_Polyurethaan Blauw, Impact plaat “Z” | J74: 09-07_Plaque d’impact profil en « Z » | K74: 09-07_Schlagabsorber Platte Z Profil, Polyurethan Blau
B75: I | D75: =IFERROR(VLOOKUP(C75,'Produktkategorien EN'!A:H,7,FALSE),"") | E75: =IFERROR(VLOOKUP(C75,'Produktkategorien EN'!A:H,5,FALSE),"") | F75: =IFERROR(VLOOKUP(C75,'Produktkategorien EN'!A:H,3,FALSE),"") | G75: I8 | H75: 09-08_T-Rex Diamond, Polyurethane Blue | I75: 09-08_T-Rex Diamond, Polyurethaan Blauw | J75: 09-08_T-Rex Diamond, Polyuréthan bleu | K75: 09-08_T-Rex Diamond, Polyurethan Blau
B76: I | D76: =IFERROR(VLOOKUP(C76,'Produktkategorien EN'!A:H,7,FALSE),"") | E76: =IFERROR(VLOOKUP(C76,'Produktkategorien EN'!A:H,5,FALSE),"") | F76: =IFERROR(VLOOKUP(C76,'Produktkategorien EN'!A:H,3,FALSE),"") | G76: I9 | H76: 09-09_T-Rex Polyurethane Yellow | I76: 09-09_ T-Rex Polyurethaan Geel | J76: 09-09_T-Rex Polyuréthane jaune | K76: 09-09_T-Rex Polyurethan Gelb
B77: I | D77: =IFERROR(VLOOKUP(C77,'Produktkategorien EN'!A:H,7,FALSE),"") | E77: =IFERROR(VLOOKUP(C77,'Produktkategorien EN'!A:H,5,FALSE),"") | F77: =IFERROR(VLOOKUP(C77,'Produktkategorien EN'!A:H,3,FALSE),"") | G77: I10 | H77: 09-10_FLUI-REX Polyurethane | I77: 09-10_FLUI-REX Polyurethaan met lijmlaag | J77: 09-10_FLUI-REX Polyuréthan avec face adhésive | K77: 09-10_FLUI-REX Polyurethan mit Kontaktschicht
B78: I | D78: =IFERROR(VLOOKUP(C78,'Produktkategorien EN'!A:H,7,FALSE),"") | E78: =IFERROR(VLOOKUP(C78,'Produktkategorien EN'!A:H,5,FALSE),"") | F78: =IFERROR(VLOOKUP(C78,'Produktkategorien EN'!A:H,3,FALSE),"") | G78: I11 | H78: 09-11_T-Rex Polyethylene, HMPE | I78: 09-11_T-Rex Polyethyleen, HMPE | J78: 09-11_T-Rex Polyethylène, HMPE | K78: 09-11_T-Rex Polyethylen, HMPE
B79: J | C79: 10_Belt Tracking | D79: =IFERROR(VLOOKUP(C79,'Produktkategorien EN'!A:H,7,FALSE),"") -> 10_Transportbandstuursystemen | E79: =IFERROR(VLOOKUP(C79,'Produktkategorien EN'!A:H,5,FALSE),"") -> 10_Centrage de bande transporteuse | F79: =IFERROR(VLOOKUP(C79,'Produktkategorien EN'!A:H,3,FALSE),"") -> 10_Fördergurt-Zentrierung | G79: J1 | H79: 10-01_Flat Return Tracker | I79: 10-01_Flat Return Tracker | J79: 10-01_Auto-centreur | K79: 10-01_Flat Return Tracker
B80: J | D80: =IFERROR(VLOOKUP(C80,'Produktkategorien EN'!A:H,7,FALSE),"") | E80: =IFERROR(VLOOKUP(C80,'Produktkategorien EN'!A:H,5,FALSE),"") | F80: =IFERROR(VLOOKUP(C80,'Produktkategorien EN'!A:H,3,FALSE),"") | G80: J2 | H80: 10-02_Tapered Trough Tracker | I80: 10-02_Tapered Trough Tracker | J80: 10-02_Auto-centreur conique en auge | K80: 10-02_Tapered Trough Tracker
B81: J | D81: =IFERROR(VLOOKUP(C81,'Produktkategorien EN'!A:H,7,FALSE),"") | E81: =IFERROR(VLOOKUP(C81,'Produktkategorien EN'!A:H,5,FALSE),"") | F81: =IFERROR(VLOOKUP(C81,'Produktkategorien EN'!A:H,3,FALSE),"") | G81: J3 | H81: 10-03_Low Speed Tracker | I81: 10-03_Low Speed Tracker | J81: 10-03_Auto-centreur de basse vitesse | K81: 10-03_Low Speed Tracker
B82: J | D82: =IFERROR(VLOOKUP(C82,'Produktkategorien EN'!A:H,7,FALSE),"") | E82: =IFERROR(VLOOKUP(C82,'Produktkategorien EN'!A:H,5,FALSE),"") | F82: =IFERROR(VLOOKUP(C82,'Produktkategorien EN'!A:H,3,FALSE),"") | G82: J4 | H82: 10-04_Dual Return Tracker | I82: 10-04_Dual Return Tracker | J82: 10-04_Auto-centreur double | K82: 10-04_Dual Return Tracker
B83: K | C83: 11_TQ Rollers | D83: =IFERROR(VLOOKUP(C83,'Produktkategorien EN'!A:H,7,FALSE),"") -> 11_TQ Rollen | E83: =IFERROR(VLOOKUP(C83,'Produktkategorien EN'!A:H,5,FALSE),"") -> 11_TQ rouleaux | F83: =IFERROR(VLOOKUP(C83,'Produktkategorien EN'!A:H,3,FALSE),"") -> 11_TQ Rolle | G83: K1 | H83: 11-01_TQ Roller HDPE Ø 89 | I83: 11-01_TQ Rollen HDPE Ø 89 | J83: 11-01_TQ Rouleaux HDPE Ø 89 | K83: 11-01_TQ Rolle HDPE Ø 89
B84: K | D84: =IFERROR(VLOOKUP(C84,'Produktkategorien EN'!A:H,7,FALSE),"") | E84: =IFERROR(VLOOKUP(C84,'Produktkategorien EN'!A:H,5,FALSE),"") | F84: =IFERROR(VLOOKUP(C84,'Produktkategorien EN'!A:H,3,FALSE),"") | G84: K2 | H84: 11-02_TQ Roller HDPE Ø 108 | I84: 11-02_TQ Rollen HDPE Ø 108 | J84: 11-02_TQ Rouleaux HDPE Ø 108 | K84: 11-02_TQ Rolle HDPE Ø 108
B85: K | D85: =IFERROR(VLOOKUP(C85,'Produktkategorien EN'!A:H,7,FALSE),"") | E85: =IFERROR(VLOOKUP(C85,'Produktkategorien EN'!A:H,5,FALSE),"") | F85: =IFERROR(VLOOKUP(C85,'Produktkategorien EN'!A:H,3,FALSE),"") | G85: K3 | H85: 11-03_TQ Roller HDPE Ø 133 | I85: 11-03_TQ Rollen HDPE Ø 133 | J85: 11-03_TQ Rouleaux HDPE Ø 133 | K85: 11-03_TQ Rolle HDPE Ø 133
B86: K | D86: =IFERROR(VLOOKUP(C86,'Produktkategorien EN'!A:H,7,FALSE),"") | E86: =IFERROR(VLOOKUP(C86,'Produktkategorien EN'!A:H,5,FALSE),"") | F86: =IFERROR(VLOOKUP(C86,'Produktkategorien EN'!A:H,3,FALSE),"") | G86: K4 | H86: 11-04_TQ Roller HDPE Ø 159 | I86: 11-04_TQ Rollen HDPE Ø 159 | J86: 11-04_TQ Rouleaux HDPE Ø 159 | K86: 11-04_TQ Rolle HDPE Ø 159
B87: L | C87: 12_Safety Products | D87: =IFERROR(VLOOKUP(C87,'Produktkategorien EN'!A:H,7,FALSE),"") -> 12_Veiligheidsproducten | E87: =IFERROR(VLOOKUP(C87,'Produktkategorien EN'!A:H,5,FALSE),"") -> 12_Produits de sécurité | F87: =IFERROR(VLOOKUP(C87,'Produktkategorien EN'!A:H,3,FALSE),"") -> 12_Schutzvorrichtungen | G87: L1 | H87: 12-01_CROC GRIP Belt Clamps | I87: 12-01_CROC GRIP Bandklemmen | J87: 12-01_CROC GRIP Pince de Bande | K87: 12-01_CROC GRIP Gurtklemme
B88: L | D88: =IFERROR(VLOOKUP(C88,'Produktkategorien EN'!A:H,7,FALSE),"") | E88: =IFERROR(VLOOKUP(C88,'Produktkategorien EN'!A:H,5,FALSE),"") | F88: =IFERROR(VLOOKUP(C88,'Produktkategorien EN'!A:H,3,FALSE),"") | G88: L2 | H88: 12-02_Conveyor Belt Covers, Steel | I88: 12-02_Transportbandoverkappingen, Staal | J88: 12-02_Capots, acier | K88: 12-02_Fördergurt Abdeckhauben, Stahl
B89: L | D89: =IFERROR(VLOOKUP(C89,'Produktkategorien EN'!A:H,7,FALSE),"") | E89: =IFERROR(VLOOKUP(C89,'Produktkategorien EN'!A:H,5,FALSE),"") | F89: =IFERROR(VLOOKUP(C89,'Produktkategorien EN'!A:H,3,FALSE),"") | G89: L3 | H89: 12-03_Conveyor Belt Covers, PVC | I89: 12-03_Transportbandoverkappingen, PVC | J89: 12-03_Capots, PVC | K89: 12-03_Fördergurt Abdeckhauben, PVC
B90: L | D90: =IFERROR(VLOOKUP(C90,'Produktkategorien EN'!A:H,7,FALSE),"") | E90: =IFERROR(VLOOKUP(C90,'Produktkategorien EN'!A:H,5,FALSE),"") | F90: =IFERROR(VLOOKUP(C90,'Produktkategorien EN'!A:H,3,FALSE),"") | G90: L4 | H90: 12-04_Inspection Door + Screen | I90: 12-04_Inspectiedeuren | J90: 12-04_Inspection par | K90: 12-04_Inspection Door + Screen

Sheet Sheet4
A1: 1 | B1: A
A2: 2 | B2: B
A3: 3 | B3: C
A4: 4 | B4: D
A5: 5 | B5: E
A6: 6 | B6: F
A7: 7 | B7: G
A8: 8 | B8: H
A9: 9 | B9: I
A10: 10 | B10: J
A11: 11 | B11: K
A12: 12 | B12: L

Sheet Sheet2
A1: Webshop laag 0 | B1: Code laag 1 | C1: Webshop laag 1 NL | D1: Webschop laag 1 FR | E1: Code laag 2 | F1: Webshop laag 2 NL | G1: Webshop laag 2 FR | H1: Intern Exact | I1: Media artist
A2: 01_Conveyor Belts
A3: 02_Profiled Conveyor Belts
A4: 03_Wear Protection
A5: 04_Drum Lagging
A6: 05_Tools
A7: 06_Vulcanization Materials
A8: 07_Repair Material
A9: 08_Belt Cleaning
A10: 09_Components
A11: 10_Belt Tracking
A12: 11_TQ Rollers
A13: 12_Safety Products
